Workbook
Name \0: #REF!
Name \a: #REF!
Name \B: #REF!
Name \C: #REF!
Name \D: #REF!
Name \E: #REF!
Name \F: #REF!
Name \G: #REF!
Name \H: #REF!
Name \I: #REF!
Name \J: #REF!
Name \K: #REF!
Name \L: #REF!
Name \M: #REF!
Name \N: #REF!
Name \O: #REF!
Name \P: #REF!
Name \Q: #REF!
Name \R: #REF!
Name \S: #REF!
Name \T: #REF!
Name \U: #REF!
Name \v: #REF!
Name \W: #REF!
Name \X: #REF!
Name \Y: #REF!
Name \Z: #REF!
Name _: {1,2,3,4;5,6,7,8;9,10,11,12;13,14,15,16}
Name _________________________________________________________________Hp3: {1,2,3,4;5,6,7,8;9,10,11,12;13,14,15,16}
Name _______________________________________________________________Hp3: {1,2,3,4;5,6,7,8;9,10,11,12;13,14,15,16}
Name _______________________________________________Hp3: {1,2,3,4;5,6,7,8;9,10,11,12;13,14,15,16}
Name _______________________________________________Hp3_1: {1,2,3,4;5,6,7,8;9,10,11,12;13,14,15,16}
Name ______________________________________________Hp3: {1,2,3,4;5,6,7,8;9,10,11,12;13,14,15,16}
Name _____________________________________________Hp3: {1,2,3,4;5,6,7,8;9,10,11,12;13,14,15,16}
Name ___________________________________________Hp3: {1,2,3,4;5,6,7,8;9,10,11,12;13,14,15,16}
Name __________________________________________Hp3: {1,2,3,4;5,6,7,8;9,10,11,12;13,14,15,16}
Name ________________________________________Hp3: {1,2,3,4;5,6,7,8;9,10,11,12;13,14,15,16}
Name _____________________________________Hp3: {1,2,3,4;5,6,7,8;9,10,11,12;13,14,15,16}
Name ____________________________________Hp3: {1,2,3,4;5,6,7,8;9,10,11,12;13,14,15,16}
Name ____________________________________Hp3_1: {1,2,3,4;5,6,7,8;9,10,11,12;13,14,15,16}
Name ___________________________________Hp3: {1,2,3,4;5,6,7,8;9,10,11,12;13,14,15,16}
Name _________________PAG2: #REF!
Name _________________PAG3: #REF!
Name _________________PAG7: #REF!
Name ________________PAG2: #REF!
Name ________________PAG3: #REF!
Name ________________PAG7: #REF!
Name _______________cla2: #REF!
Name _______________PAG2: #REF!
Name _______________PAG3: #REF!
Name _______________PAG7: #REF!
Name ______________cla2: #REF!
Name ______________PAG2: #REF!
Name ______________PAG3: #REF!
Name ______________PAG7: #REF!
Name _____________cla2: #REF!
Name _____________PAG2: #REF!
Name _____________PAG3: #REF!
Name _____________PAG7: #REF!
Name _____________R: #REF!

Sheet PORTADA
F1: VISADO CONTROL CRÉDITO
A3: INFORME DE TASACIÓN
F7: FECHA TASACIÓN:
F8: UF BASE:
F9: Valor USD
F10: Informe: | H10: Retasación
F11: Comuna
F12: Región
A14: CLIENTE: | G14: RUT:
A15: PROPIETARIO: | G15: RUT:
A17: Nº | B17: Nombre de la Propiedad | F17: Rol Avalúo | G17: Comuna | H17: Superf. Legal (ha) | I17: Superf. Real (ha)
A18: 1 | B18: =LEGAL!B6 | F18: =LEGAL!G6 | G18: =PORTADA!H11 | H18: =LEGAL!H6 | I18: =LEGAL!I6
A19: 2
A20: 3
F21: Total (ha) | H21: =SUM(H18:H20) | I21: =SUM(I18:I20)
A23: RESUMEN DE VALORES | D23: USD | F23: $ | H23: UF
A24: Suelos | D24: =F24/USD | F24: ='RESUMEN VALOR'!C6 | H24: =F24/UF
A25: Derechos de Agua | D25: =F25/USD | F25: ='AGUA '!J27 | H25: =F25/UF
A26: Infraestructura Hipotecable | D26: =F26/USD | F26: =CONSTR!S11 | H26: =F26/UF
A27: Infraestructura Prendable | D27: =F27/USD | F27: =CONSTR!S18 | H27: =F27/UF
A28: Plantaciones sin royalty | D28: =F28/USD | F28: =PLANTACION!H11 | H28: =F28/UF
A29: Plantaciones con royalty | D29: =F29/USD | F29: =PLANTACION!H17 | H29: =F29/UF
A30: Instalaciones - Equipos | D30: =F30/USD | F30: =CONSTR!S23 | H30: =F30/UF
A31: Valor Comercial | D31: =F31/USD | F31: =SUM(F24:G30) | H31: =F31/UF
A32: Valor comercial/ha | D32: =D31/$H$21 | F32: =F31/$H$21 | H32: =H31/$H$21
A33: Valor Liquidación | D33: ='RESUMEN VALOR'!E20 | F33: ='RESUMEN VALOR'!E19 | H33: ='RESUMEN VALOR'!E21
A36: OBSERVACIONES Y ADVERTENCIAS

Sheet LEGAL
A1: 2.-ANTECEDENTES LEGALES
A3: 2.1. ANTECEDENTES DEL DOMINIO E HIPOTECAS
A4: nº | B4: PROPIEDADES | C4: Inscripción dominio | F4: C.B.R. | G4: Rol SII | H4: Superficie Legal/SII (ha) | I4: Medición Satelital (ha) | J4: Hipoteca Rabofinance | K4: Tasación anterior | L4: Deuda de Contribuciones
C5: fs | D5: nº | E5: año
A6: 1 | I6: =H6
A7: =+A6+1
A8: 3
A9: 4
A10: 5
A11: 6
G12: TOTAL | H12: =SUM(H6:H11) | I12: =SUM(I6:I11) | L12: =SUM(L6:L11)
A14: OBSERVACIONES
A21: 2.2. ANTECEDENTES EXPROPIATORIOS:
A22: nº | B22: PROPIEDADES | C22: Afecto a Expropiación | E22: Superficie expropiada | G22: Franja y vía afecta a expropiación
A24: 1
A25: =+A24+1
A26: =+A25+1
A27: =+A26+1
A28: =+A27+1
A33: 2.3. DESLINDES LEGALES
A34: nº | B34: PROPIEDADES | C34: DESLINDES LEGALES
A35: =A6 | B35: =+B6
A36: =A7
A38: CERTIFICADO DE AVALÚO DEL SII Y CERTIFICADO DE DEUDA TGR

Sheet SUELOS  
A1: 3.- SUELOS
A33: 3.1.Descripción General Suelos
G34: Tipo propiedad: | H34: AGRÍCOLA
G35: Coordenada E
G36: Coordenada S
G37: Ciudad + cercana:
G38: Distancia
G39: Ruta de acceso
G40: Tipo de vía
A43: 3.2. VALOR SUELOS
A44: Propiedad | B44: Rol | C44: Clase | D44: Grado de | E44: Superficie | F44: Valor Unitario | G44: TOTAL
B45: SII | C45: Uso | D45: Habilitación | E45: m2 | F45: UF/m2 | G45: $ | H45: USD
G46: =F46*E46*UF | H46: =G46/USD
G47: =F47*E47*UF | H47: =G47/USD
G48: =F48*E48 | H48: =G48/USD
G49: =F49*E49 | H49: =G49/USD
G50: =F50*E50 | H50: =G50/USD
G51: =F51*E51 | H51: =G51/USD
G52: =F52*E52 | H52: =G52/USD
G53: =F53*E53 | H53: =G53/USD
C54: m2 | E54: =SUM(E46:E53) | G54: =SUM(G46:G53) | H54: =SUM(H46:H53)
C55: ha | E55: =E54/10000
A57: 3.4. MOSAICO DE ROLES
A59: PERÍMETRO,CLASIFICACIÓN DE USO DE SUELOS Y UBICACIÓN DENTRO DEL PRC, SEGÚN CARTOGRAFÍA DE CIREN (visor.sitrural.cl)
B308: Rol SII | C308: Zona | E308: Superf. m2 | F308: Valor UF/m2 | G308: Total $
E314: =SUM(E309:E313) | G314: =SUM(G309:G313)
G315: =G314/USD
C317: TOTAL | E317: =+E54+E314 | F317: m2 | G317: =G54+G314
G318: =G317/USD

Sheet AGUA 
A1: 4.- DERECHOS DE AGUA
A4: 4.1. INSCRIPCIÓN DE DERECHOS DE AGUA
A5: N° | B5: FUENTE | C5: Rol | D5: Derechos* | E5: Tipo | F5: Inscrito en | G5: Hipotecados a Rabofinance | H5: Datos de Inscripción | K5: CBR
C6: Avalúo | D6: Cantidad | F6: CPA | H6: fojas | I6: nº | J6: año
A7: 1
A8: 2
A9: 3
A10: 5
A11: 4
A13: Observaciones:
A22: 4.2. VALOR DE DERECHOS DE AGUA
A23: N° | B23: Fuente | C23: ROL | D23: Derechos | E23: Tipo | F23: Derechos expresados en acción | G23: Caudal Nominal (L/s) | H23: Hipotecados a Rabofinance | I23: Valor Unitario $ | J23: Total
C24: Avalúo | D24: Cantidad | J24: $ | K24: USD
A25: 1 | J25: =G25*I25 | K25: =J25/USD
A26: 4
B27: Total Derechos de Agua | G27: =SUM(G25:G26) | H27: =SUM(H25:H26) | J27: =SUM(J25:J26) | K27: =SUM(K25:K26)
A31: SUFICIENCIA DE DERECHOS DE AGUA
A36: INFORMACIÓN GENERAL DE LOS DERECHOS DE AGUA, IMAGEN DE EMPLAZAMIENTO PUNTO DE CAPTACIÓN

Sheet CONSTR
A3: 5- DESCRIPCIÓN DE INFRAESTRUCTURA E INSTALACIONES | P3: USD | Q3: =USD | R3: UF | S3: =UF
A4: 5.1.- CONSTRUCCIONES HIPOTECABLES
A5: N° | B5: EDIFICACIONES | C5: Estado conservación | D5: Ubicación Rol | E5: Superficie m2 | F5: Estructura Vertical Principal | G5: Data Aprox. | H5: Estructura Techumbre | I5: Pavimentos | J5: Cubierta | K5: Revestimiento Vertical | L5: Bien asegurable Sí/NO | M5: Costo Reposición UF/m2 | N5: Vida Útil Total (años) | O5: Vida remanente (años) | P5: Valor residual estimado % | Q5: Valor Unitario depreciado UF/m2 | R5: Valor Unitario $/m2 | S5: Valor Total Actual $
A6: 1
A7: 2
A8: 3
A9: 4
A10: 5
B11: Superficie Total | E11: =SUM(E6:E10) | S11: =SUM(S6:S10)
S12: =S11/$Q$3
A13: 5.2.- CONSTRUCCIONES PRENDABLES
A14: N° | B14: EDIFICACIONES | C14: Estado conservación | D14: Ubicación Rol | E14: Superficie m2 | F14: Estructura Vertical Principal | G14: Data Aprox. | H14: Estructura Techumbre | I14: Pavimentos | J14: Cubierta | K14: Revestimiento Vertical | L14: Bien asegurable Sí/NO | M14: Costo Reposición UF/m2 | N14: Vida Útil Total (años) | O14: Vida remanente (años) | P14: Valor residual estimado % | Q14: Valor Unitario depreciado UF/m2 | R14: Valor Unitario $/m2 | S14: Valor Total Actual $
A15: 1
A16: 2
B18: Superficie Total | E18: =SUM(E15:E17) | S18: =SUM(S15:S17)
S19: =S18/$Q$3
A20: 5.3.- INSTALACIONES Y OBRAS COMPLEMENTARIAS
A21: N° | B21: ÍTEM | C21: Estado conservación | D21: Ubicación Rol | E21: Cantidad | F21: Unidad | G21: Data Aprox. | H21: Descripción General | L21: Bien asegurable Sí/NO | M21: Costo Reposición Unitario UF | N21: Vida Útil Total (años) | O21: Vida remanente (años) | P21: Valor residual estimado | Q21: Valor Unitario depreciado | R21: Valor Unitario $ | S21: Valor Total Actual $
A22: 1 | O22: =IFERROR(IF((G22+N22-YEAR(PORTADA!$H$7))<0,0,G22+N22-YEAR(PORTADA!$H$7)),"") | Q22: =M22*(P22+(1-P22)*O22/N22) | R22: =Q22*$S$3 | S22: =R22*E22 | U22: =Q22/M22
B23: Superficie Total | E23: =SUM(E22:E22) | S23: =SUM(S22:S22)
S24: =S23/$Q$3
A26: OBSERVACIONES :
A35: 5.4. EMPLAZAMIENTO DE LAS EDIFICACIONES

Sheet PLANTACION
A1: 6.- PLANTACIONES
A3: 6.1. PLANTACIONES SIN ROYALTIES
A4: ESPECIE | B4: VARIEDAD | C4: AÑO | D4: Densidad plantas/ha | E4: ROL | F4: Superficie ha | G4: VALOR UNITARIO $/ha | H4: TOTAL $ | I4: TOTAL UF | J4: TOTAL USD | K4: Estado Plantación
G5: =PLANT!AA37 | H5: =F5*G5 | I5: =H5/UF | J5: =H5/USD
G6: =PLANT!AA38 | H6: =F6*G6 | I6: =H6/UF | J6: =H6/USD
G7: =PLANT!AA39 | H7: =F7*G7 | I7: =H7/UF | J7: =H7/USD
G8: =PLANT!AA40 | H8: =F8*G8 | I8: =H8/UF | J8: =H8/USD
G9: =PLANT!AA41 | H9: =F9*G9 | I9: =H9/UF | J9: =H9/USD
G10: =PLANT!AA42 | H10: =F10*G10 | I10: =H10/UF | J10: =H10/USD
D11: TOTALES | F11: =SUM(F5:F10) | H11: =SUM(H5:H10) | I11: =SUBTOTAL(9,I5:I10) | J11: =SUBTOTAL(9,J5:J10)
A13: 6.2. PLANTACIONES CON ROYALTIES
A14: ESPECIE | B14: VARIEDAD | C14: AÑO | D14: MARCO DE PLANTACIÓN | E14: ROL | F14: Superficie ha | G14: VALOR UNITARIO $/ha | H14: TOTAL $ | I14: TOTAL UF | J14: TOTAL USD | K14: Estado Plantación
F17: =SUM(F15:F16) | H17: =SUM(H15:H16) | I17: =SUM(I15:I16) | J17: =SUM(J15:J16)
A19: OBSERVACIONES
A24: DIFERENCIAS CON TASACIÓN ANTERIOR

Sheet RESUMEN VALOR
A1: RESUMEN DE VALORES
A4: =LEGAL!G6 | B4: =LEGAL!B6
A5: HIPOTECA | C5: VALOR COMERCIAL $ | D5: AJUSTE % | E5: VALOR LIQUIDACIÓN $
B6: SUELOS | C6: ='SUELOS '!G54 | D6: 0.7 | E6: =C6*D6
B7: DERECHOS DE AGUA | C7: ='AGUA '!J27 | D7: 0.7 | E7: =C7*D7
B8: DERECHOS DE AGUA SIN HIPOTECAR | D8: 0.7 | E8: =C8*D8
B9: INFRAESTRUCTURA HIPOTECABLE | C9: =SUMIF(CONSTR!$D$6:$D$10,'RESUMEN VALOR'!A4,CONSTR!$S$6:$S$10) | D9: 0.7 | E9: =C9*D9
B10: Total Hipoteca | C10: =SUM(C6:C9) | E10: =SUM(E6:E9)
A12: PRENDA | C12: VALOR COMERCIAL $ | D12: AJUSTE % | E12: VALOR LIQUIDACIÓN $
B13: PLANTACIONES | C13: =PLANTACION!H11 | D13: 0.5 | E13: =C13*D13
B14: PLANTACIONES CON ROYALTY | C14: =SUMIF(PLANTACION!$E$15:$E$16,'RESUMEN VALOR'!A4,PLANTACION!$H$15:$H$16) | D14: 0.5 | E14: =C14*D14
B15: INFRAESTRUCTURA PRENDABLE | C15: =SUMIF(CONSTR!$D$15:$D$17,'RESUMEN VALOR'!A4,CONSTR!$S$15:$S$17) | D15: 0.5 | E15: =C15*D15
B16: EQUIPOS E INSTALACIONES | C16: =SUMIF(CONSTR!$D$22:$D$22,'RESUMEN VALOR'!A4,CONSTR!$S$22:$S$22) | D16: 0.5 | E16: =C16*D16
B17: Total Prenda | C17: =SUM(C13:C16) | E17: =SUM(E13:E16)
B19: TOTAL | C19: =C17+C10 | E19: =E17+E10
B20: USD | C20: =C19/USD | E20: =E19/USD
B21: UF | C21: =C19/UF | E21: =E19/UF
A24: NOMBRE TASADOR | D24: FECHA | E24: =PORTADA!H7
A25: RUT | D25: DÓLAR | E25: =USD
A26: Empresa | C26: FIRMA | D26: UF | E26: =UF

Sheet Fotografias 1
B1: FOTOGRAFÍAS

Sheet REF. PROPIEDADES 
A2: REFERENCIAS DE MERCADO | G2: UF: | H2: =PORTADA!$H$8 | K2: USD | L2: =PORTADA!$H$9
A5: Ubicación | B5: Región | C5: Comuna | D5: Superficie (m2) | E5: Valor Total Publicado M$ | F5: Valor Total Publicado UF | G5: Fecha | H5: Tipo de Referencia | I5: Valor Total Ajustado UF | J5: Superf. edificada m2 | K5: Valor edificado UF/m2 | L5: Valor Depurado UF | M5: Valor Depurado UF/m2 | N5: Link oferta o datos compraventa (fs/nº/año/CBR) | O5: Breve descripción | P5: Referencia
A6: Ruta 5 Norte km 109 | B6: V | C6: Hijuelas | D6: 33000 | E6: =F6*H2/1000 | F6: 70000 | G6: 44225 | H6: Oferta | L6: =IF(H6="Oferta",F6*$F$229-(J6*K6),F6) | M6: =L6/D6 | N6: https://www.toctoc.com/propiedades/compracorredorasr/terreno/hijuelas/ruta-5-norte-hijuelas/1139997?utm_source=Lifull-connect&utm_medium=referrer | O6: Terreno plano, sin construcciones en enlace sur a Hijuelas.
A7: Ruta 5 norte | B7: V | C7: Hijuelas | D7: 10000 | E7: 270000 | F7: =E7*1000/H2 | G7: 44221 | H7: Oferta | L7: =IF(H7="Oferta",F7*$F$229-(J7*K7),F7) | M7: =L7/D7 | N7: http://www.ewilde.cl/propiedad/terreno-industrial-hijuelas/105 | O7: Poniente de ruta 5 norte, acceso por caletera.
A8: Chonchi | B8: X | C8: Chonchi | D8: 10000 | E8: 220000 | F8: =E8*1000/$H$2 | G8: 44856 | H8: Oferta | L8: =IF(H8="Oferta",F8*$F$229-(J8*K8),F8) | M8: =L8/D8 | N8: http://www.economicos.cl/propiedades/vendo-propiedad-industrial-en-chonchi-codAATIN6Q.html | O8: Propiedad industrial, con 300 m2 construidos con instalaciones relacionadas al rubro
A9: Castro | B9: X | C9: Castro | D9: 6890 | E9: 220000 | F9: =E9*1000/$H$2 | G9: 44877 | H9: Oferta | L9: =IF(H9="Oferta",F9*$F$229-(J9*K9),F9) | M9: =L9/D9 | N9: http://www.economicos.cl/propiedades/propiedad-industrial-en-venta-en-castro-codR76244956-0L0-21546.html | O9: Sector industrial entrada de Castro, acceso directo desde Ruta 5, cuenta con APR y con factibilidad de tendido trifásico.
A10: Calbuco | B10: X | C10: Calbuco | D10: 1300 | E10: 880000 | F10: 25000 | G10: 44958 | H10: Oferta | I10: =IF(H10="Oferta",F10*$F$229,F10) | J10: 1300 | K10: 15 | L10: =I10-J10*K10 | M10: =L10/D10 | N10: https://www.economicos.cl/propiedades/planta-procesadora-de-pescados-y-mariscos-codAATQBUI.html | O10: planta procesadora de pescado y marisco | P10: Ref ind 2025-171101
A11: Terreno en Tomé | B11: VIII | C11: Tomé | D11: 52924 | E11: =F11*$H$2/1000 | F11: 35000 | G11: 46143 | H11: Oferta | I11: =IF(H11="Oferta",F11*$F$229,F11) | J11: 0 | K11: 0 | L11: =I11-J11*K11 | M11: =L11/D11 | N11: https://www.portalinmobiliario.com/MLC-4112426366-remate-tome-terreno-calle-1-n493-lt-f-aysen-493-lt-g-_JM#polycard_client=search-desktop&be_origin=backend&search_layout=grid&position=10&type=item&tracking_id=627efe66-4b1a-4725-a564-d2472dfe928b&price_drop=true&sid=search | O11: se emplaza en la parte alta del cerro al norte de playa El Morro, cerca del acceso a Villa Cocholgüe, sin habilitar. | P11: Ref ind 2026-010701
A12: Terreno en Tomé | B12: VIII | C12: Tomé | D12: 5046 | E12: =F12*$H$2/1000 | F12: 19679 | G12: 45474 | H12: Oferta | I12: =IF(H12="Oferta",F12*$F$229,F12) | J12: 0 | K12: 0 | L12: =I12-J12*K12 | M12: =L12/D12 | N12: https://www.portalinmobiliario.com/MLC-1709335365-venta-de-terreno-en-tome-id-51987-lin-_JM#polycard_client=search-desktop&be_origin=backend&search_layout=grid&position=8&type=item&tracking_id=627efe66-4b1a-4725-a564-d2472dfe928b&price_drop=not_apply&sid=search | O12: Usos permitidos: Residencial y Equipamiento. Coeficiente ocupación de suelo: 40%. Coeficiente Constructibilidad 0,8. Densidad bruta: 100 hab/ha. Sup. Radial mínima: 500 | P12: Ref ind 2026-010702
A13: Propiedad en Ruta H-233, cercano a predio tasado | B13: VI | C13: Rancagua | D13: 140000 | E13: =F13*$H$2/1000 | F13: 91000 | G13: 46067 | H13: Oferta | I13: =IF(H13="Oferta",F13*$F$229,F13) | J13: 0 | K13: 0 | L13: =I13-J13*K13 | M13: =L13/D13 | N13: https://www.portalinmobiliario.com/MLC-3575446050-terreno-construccion-en-venta-en-rancagua-_JM#polycard_client=search-map&price_drop=not_apply&be_origin=backend&overlay_label=not_apply&search_layout=map&position=3&type=item&tracking_id=e2c67754-051a-4587-9a99-a09429be5d83&sid=search | O13: sector La Cruz, terreno ZEUES con posibildad de venta de lote de menor tamaño, mismo sector tasado
A14: Propiedad en Ruta H-233, cercano a predio tasado | B14: VI | C14: Rancagua | D14: 9800 | E14: =F14*$H$2/1000 | F14: 6370 | G14: 46067 | H14: Oferta | I14: =IF(H14="Oferta",F14*$F$229,F14) | J14: 0 | K14: 0 | L14: =I14-J14*K14 | M14: =L14/D14 | N14: https://www.portalinmobiliario.com/MLC-3575393050-terreno-construccion-en-venta-en-rancagua-_JM#polycard_client=search-map&price_drop=not_apply&be_origin=backend&overlay_label=not_apply&search_layout=map&position=6&type=item&tracking_id=e2c67754-051a-4587-9a99-a09429be5d83&sid=search | O14: sector La Cruz, terreno ZEUES con servicios básicos , mismo sector tasado
A15: Terreno plano, con proyecto inmobiliario en Ruta H-200 | B15: VI | C15: Rancagua | D15: 139400 | E15: =F15*$H$2/1000 | F15: 209100 | G15: 46067 | H15: Oferta | I15: =IF(H15="Oferta",F15*$F$229,F15) | J15: 0 | K15: 0 | L15: =I15-J15*K15 | M15: =L15/D15 | N15: https://www.portalinmobiliario.com/MLC-3336689894-terreno-san-ramon-proyecto-inmobiliario-_JM#polycard_client=search-map&price_drop=not_apply&be_origin=backend&overlay_label=not_apply&search_layout=map&position=5&type=item&tracking_id=3f11ce2a-e7f6-4a3c-8c8f-85900534085d&sid=search | O15: cercano a centro de la ciudad, uso mixto, zona en crecimiento
A16: Propiedad en zona ZEUES y AR-1, Ruta H-201 | B16: VI | C16: Rancagua | D16: =41.1*10000 | E16: =F16*$H$2/1000 | F16: 61000 | G16: 46217 | H16: Oferta | I16: =IF(H16="Oferta",F16*$F$229,F16) | J16: 0 | K16: 0 | L16: =I16-J16*K16 | M16: =L16/D16 | N16: https://www.portalinmobiliario.com/MLC-4188275772-oportunidad-de-inversion-en-terreno-amplio-170406-_JM#polycard_client=search-map&price_drop=not_apply&be_origin=backend&overlay_label=not_apply&search_layout=map&position=34&type=item&tracking_id=3f11ce2a-e7f6-4a3c-8c8f-85900534085d&sid=search | O16: terreno de 41,1 ha ubicado sector El Crucero, en zona ZEUES y AR1, similar al predio tasado, con acciones de canal, con construciones
A17: Predio de uso agrícola | B17: VI | C17: Rancagua | D17: =19.61*10000 | E17: 980500 | F17: 24032.705 | G17: 46036 | H17: Oferta | I17: =IF(H17="Oferta",F17*$F$229,F17) | J17: 0 | K17: 0 | L17: =I17-J17*K17 | M17: =L17/D17 | N17: https://www.portalinmobiliario.com/MLC-3505579952-agricola-en-venta-en-rancagua-_JM#polycard_client=recommendations_classi-realestate-vip&reco_backend=realestate-odin&reco_model=organicos-vis&reco_client=classi-realestate-vip&reco_item_pos=0&reco_backend_type=function&reco_id=16ac6830-2d5f-4850-9cf4-19133cc67fa7&sid=recos | O17: Propiedad agrícola, suelos planos, con derechos de agua
A18: Parcela cercana a predio tasado, Ruta H-15-G | B18: VI | C18: Rancagua | D18: 5000 | E18: 220000 | F18: 5392.3459 | G18: 46247 | H18: Oferta | I18: =IF(H18="Oferta",F18*$F$229,F18) | J18: 0 | K18: 0 | L18: =I18-J18*K18 | M18: =L18/D18 | N18: https://www.portalinmobiliario.com/MLC-4342889654-amplitud-y-naturaleza-en-un-lugar-unico-179096-_JM#polycard_client=search-map&price_drop=not_apply&be_origin=backend&overlay_label=not_apply&search_layout=map&position=6&type=item&tracking_id=f23461ee-dc1e-411b-9386-30d421f3ff14&sid=search | O18: terreno plano, mismo sector tasado
A19: Propiedad agrícola Coltauco | B19: VI | C19: Rancagua | D19: 35800 | E19: 275390.35 | F19: 6750 | G19: 46247 | H19: Oferta | I19: =IF(H19="Oferta",F19*$F$229,F19) | J19: 0 | K19: 0 | L19: =I19-J19*K19 | M19: =L19/D19 | N19: https://www.engelvoelkers.com/cl/es/exposes/c25f1ad3-44a1-5c0a-a91c-8ec1906bda6f | O19: terreno plano, plantado con alfalfa, acceso por ruta H 30
A20: Propiedad cercana a estadio Marista | B20: VI | C20: Rancagua | D20: 22000 | E20: 334548.27 | F20: 8200 | G20: 46247 | H20: Oferta | I20: =IF(H20="Oferta",F20*$F$229,F20) | J20: 0 | K20: 0 | L20: =I20-J20*K20 | M20: =L20/D20 | N20: https://www.engelvoelkers.com/cl/es/exposes/ae8247fc-3566-59b0-98da-70cbb564e3b6 | O20: terreno plano, cercano al sector tasado, sin plantaciones, con derechos de agua
A21: Terreno en Tomé | B21: VIII | C21: Tomé | D21: 45000 | E21: =F21*$H$2/1000 | F21: 202500 | G21: 46174 | H21: Oferta | I21: =IF(H21="Oferta",F21*$F$229,F21) | J21: 0 | K21: 0 | L21: =I21-J21*K21 | M21: =L21/D21 | N21: https://www.toctoc.com/propiedades/compracorredorasr/terreno/tome/gran-lote-gran-vista-al-mar-en-tome/3ab54e9c4b51c5cbaa15536968469c4901c302a6?utm_source=venta%2Fterreno%2Ftome | O21: Lote colindante con la propiedad, sector oriente, sin habilitar, con vegetación y pendiente | P21: Ref ind 2026-090701
A22: Terreno en Tomé | B22: VIII | C22: Tomé | D22: 4445 | E22: =F22*$H$2/1000 | F22: 16000 | G22: 45474 | H22: Oferta | I22: =IF(H22="Oferta",F22*$F$229,F22) | J22: 0 | K22: 0 | L22: =I22-J22*K22 | M22: =L22/D22 | N22: https://www.portalinmobiliario.com/MLC-1709451087-venta-de-terreno-en-tome-id-51986-lin-_JM#polycard_client=search-desktop&be_origin=backend&search_layout=grid&position=7&type=item&tracking_id=627efe66-4b1a-4725-a564-d2472dfe928b&price_drop=not_apply&sid=search | O22: Usos permitidos: Residencial y Equipamiento. Coeficiente ocupación de suelo: 40%. Coeficiente Constructibilidad 0,8. Densidad bruta: 100 hab/ha. Sup. Radial mínima: 500 | P22: Ref ind 2026-010703
A23: Terreno en Tomé | B23: VIII | C23: Tomé | D23: 107772 | E23: =F23*$H$2/1000 | F23: 27500 | G23: 45870 | H23: Oferta | I23: =IF(H23="Oferta",F23*$F$229,F23) | J23: 0 | K23: 0 | L23: =I23-J23*K23 | M23: =L23/D23 | N23: https://www.portalinmobiliario.com/MLC-2950222766-venta-de-terreno-urbano-en-tome-id-77323-lin-_JM#polycard_client=search-desktop&be_origin=backend&search_layout=grid&position=5&type=item&tracking_id=627efe66-4b1a-4725-a564-d2472dfe928b&price_drop=not_apply&sid=search | O23: Terreno urbano ubicado en la comuna de Tomé, ideal para el desarrollo de proyectos habitacionales | P23: Ref ind 2026-010704
A24: Terreno en Tomé | B24: VIII | C24: Tomé | D24: 661 | E24: 119000 | F24: =E24*1000/$H$2 | G24: 45108 | H24: Oferta | I24: =IF(H24="Oferta",F24*$F$229,F24) | J24: 0 | K24: 0 | L24: =I24-J24*K24 | M24: =L24/D24 | N24: https://www.portalinmobiliario.com/MLC-3221771482-venta-de-terreno-san-jose-del-mar-_JM#polycard_client=search-desktop&be_origin=backend&search_layout=grid&position=9&type=item&tracking_id=627efe66-4b1a-4725-a564-d2472dfe928b&price_drop=not_apply&sid=search | O24: terreno en zona urbana, semiplano, sin habilitar | P24: Ref ind 2026-010705
A25: Terreno urbano | B25: VIII | C25: Tomé | D25: 82000 | E25: =F25*$H$2/1000 | F25: 98400 | G25: 45246 | H25: Oferta | I25: =IF(H25="Oferta",F25*$F$229,F25) | J25: 0 | K25: 0 | L25: =I25-J25*K25 | M25: =L25/D25 | N25: https://www.economicos.cl/propiedades/vendo-terreno-para-inversion-en-tome-codAAUDGTQ.html | O25: 82.000 m2 de terreno urbano, en el camio entre Tomé y Coliumo, a orilllas de carretera principal | P25: Ref ind 2026-010706
A26: Terreno urbano | B26: VIII | C26: Tomé | D26: 4255 | E26: =F26*$H$2/1000 | F26: 9600 | G26: 46165 | H26: Oferta | I26: =IF(H26="Oferta",F26*$F$229,F26) | J26: 0 | K26: 0 | L26: =I26-J26*K26 | M26: =L26/D26 | N26: https://inmueble.mercadolibre.cl/MLC-4012877246-venta-terreno-sitio-4255mts-tome-_JM#polycard_client=search-desktop&be_origin=backend&search_layout=grid&position=28&type=item&tracking_id=ba0217bd-06eb-4bc1-b47c-3b53218b6b14&price_drop=not_apply&sid=search | O26: Terreno plano, sin construcciones, sector urbano, calle Los Cerezos | P26: Ref ind 2026-010707
A27: Terreno urbano | B27: VIII | C27: Tomé | D27: 19390 | E27: =F27*$H$2/1000 | F27: =2*D27 | G27: 46054 | H27: Oferta | I27: =IF(H27="Oferta",F27*$F$229,F27) | J27: 0 | K27: 0 | L27: =I27-J27*K27 | M27: =L27/D27 | N27: https://inmueble.mercadolibre.cl/MLC-1834433249-venta-de-terreno-en-tome-id-82655-lin-_JM#polycard_client=search-desktop&be_origin=backend&search_layout=grid&position=4&type=item&tracking_id=77beb2c4-3168-46f3-9b70-b4cdafabb769&price_drop=not_apply&sid=search | O27: Coef. Constructibilidad: 4.4 Coef. Ocupación de Suelo: 0.2 Densidad: Libre Sup. Predial Mínima: 2.500 m² Altura Máxima: 7 m | P27: Ref ind 2026-010708
A28: Terreno urbano | B28: VIII | C28: Tomé | D28: 125900 | E28: =F28*$H$2/1000 | F28: 88130 | G28: 46196 | H28: Oferta | I28: =IF(H28="Oferta",F28*$F$229,F28) | J28: 0 | K28: 0 | L28: =I28-J28*K28 | M28: =L28/D28 | N28: https://www.portalinmobiliario.com/MLC-4105687354-terreno-para-desarrollo-inmobiliario-_JM#polycard_client=search-desktop&be_origin=backend&search_layout=grid&position=11&type=item&tracking_id=627efe66-4b1a-4725-a564-d2472dfe928b&price_drop=not_apply&sid=search | O28: lomaje suave en el interior costero entre tomé y Dichato, 8 ha de zona residencial mixta para subdividir en hasta 300 mt2 | P28: Ref ind 2026-010709
A29: Terreno urbano | B29: VIII | C29: Tomé | D29: 4200 | E29: =F29*$H$2/1000 | F29: 12637 | G29: 45901 | H29: Oferta | I29: =IF(H29="Oferta",F29*$F$229,F29) | J29: 0 | K29: 0 | L29: =I29-J29*K29 | M29: =L29/D29 | N29: https://inmueble.mercadolibre.cl/MLC-3106130606-venta-de-terreno-en-tome-id-77016-lin-_JM#polycard_client=search-desktop&be_origin=backend&search_layout=grid&position=7&type=item&tracking_id=77beb2c4-3168-46f3-9b70-b4cdafabb769&price_drop=not_apply&sid=search | O29: terreno urbano, calle Los Nogales 1196, Tome | P29: Ref ind 2026-010710
A30: Castro, terreno industrial Ruta 5 Sur | B30: X | C30: Castro | D30: 5000 | E30: =F30*H2/1000 | F30: 9800 | G30: 45978 | H30: Oferta | I30: =IF(H30="Oferta",F30*$F$229,F30) | J30: 0 | L30: =I30-J30*K30 | M30: =L30/D30 | N30: https://inmobisur.cl/propiedad/detalle/terreno-industrial-para-venta-1615 | O30: Terreno plano, sin construcciones, sector uso industrial | P30: Ref ind 2025-171102
A31: Parcela sector Huitauque | B31: X | C31: Chonchi | D31: 7271 | E31: 86000 | F31: =E31*1000/H2 | G31: 45978 | H31: Oferta | J31: 0 | L31: =IF(H31="Oferta",F31*$F$229-(J31*K31),F31) | M31: =L31/D31 | N31: https://cl.portalterreno.com/propiedad/venta/parcela/chonchi/293828-excelente-parcela-vistas-al-mar-quinched-chiloe | O31: terreno cercano al mar, sin habilitar | P31: Ref ind 2025-171103
A32: Terreno con playa en Chonchi | B32: X | C32: Chonchi | D32: 16100 | E32: =F32*H2/1000 | F32: 9660 | G32: 45978 | H32: Oferta | I32: =IF(H32="Oferta",F32*$F$229,F32) | J32: 0 | L32: =I32-J32*K32 | M32: =L32/D32 | N32: https://calvacindustrial.cl/propiedad/se-vende-espectacular-terreno-161ha-en-chonchi-con-acceso-a-la-playa/ | O32: terreno con acceso a playa, cercano a Chonchi, sin habilitar, sin construcciones | P32: Ref ind 2025-171104
A33: Terreno cercano a Ruta 5 | B33: X | C33: Chonchi | D33: 20700 | E33: 230000 | F33: 5802 | G33: 45978 | H33: Oferta | I33: =IF(H33="Oferta",F33*$F$229,F33) | J33: 0 | L33: =I33-J33*K33 | M33: =L33/D33 | N33: https://cl.portalterreno.com/propiedad/venta/sitio/chonchi/346206-ruta-5-sur-a-38-km-de-la-ciudad-de-castro | O33: terreno con acceso directo al río, sector Llau Llao, sin habilitar | P33: Ref ind 2025-171105
A34: Terreno en Quemchi | B34: X | C34: Quemchi | D34: 5100 | E34: 41943 | F34: 1058 | G34: 45474 | H34: Oferta | J34: 0 | L34: =IF(H34="Oferta",F34*$F$229-(J34*K34),F34) | M34: =L34/D34 | N34: https://www.toctoc.com/propiedades/compracorredorasr/terreno/quemchi/sitio-en-venta-en-quemchi/5a5e157f36fffcbb5c464fba1addd2f2e5d2806e | O34: terreno cercano a playa, con acceso a servicios básicos | P34: Ref ind 2025-171106
A35: Terreno industrial Mocopulli | B35: X | C35: Dalcahue | D35: 5000 | E35: 376614 | F35: 9500 | G35: 45950 | H35: Oferta | I35: =IF(H35="Oferta",F35*$F$229,F35) | J35: 0 | L35: =I35-J35*K35 | M35: =L35/D35 | N35: https://www.toctoc.com/propiedades/compracorredorasr/terreno/dalcahue/sitio-industrial-en-venta-en-dalcahue/f329050c465e9face18c027da2bc68ef24a8a378 | O35: terrenos industriales en Mocopulli, cercano a aeropuerto y Ruta 5 Sur | P35: Ref ind 2025-171107
A36: Terreno industrial Puerto Montt | B36: X | C36: Puerto Montt | D36: 34190 | E36: =F36*H2/1000 | F36: 67250 | G36: 45979 | H36: Oferta | I36: =IF(H36="Oferta",F36*$F$229,F36) | J36: 0 | L36: =I36-J36*K36 | M36: =L36/D36 | N36: http://www.economicos.cl/propiedades/sitio-o-terreno-en-venta-en-puerto-montt-codR77087734-2L0-37065.html | O36: conformado por dos terrenos semiplanos, con construcciones | P36: Ref ind 2025-181101
A37: Terreno en Calbuco | B37: X | C37: Puerto Montt | D37: 12288 | E37: 450000 | F37: =E37*1000/$H$2 | G37: 45980 | H37: Oferta | I37: =IF(H37="Oferta",F37*$F$229,F37) | J37: 0 | L37: =I37-J37*K37 | M37: =L37/D37 | N37: https://www.coldwellbanker.cl/propiedad/detalle/terreno-ruta-5-puerto-montt-9531 | O37: terreno plano, sin habilitar, sector industrial y comercial, cercano a aeropuerto | P37: Ref ind 2025-191102
A38: Propiedad industrial en Calbuco | B38: X | C38: Puerto Montt | D38: 7000 | E38: 1500000 | F38: =E38*1000/$H$2 | G38: 45980 | H38: Oferta | I38: =IF(H38="Oferta",F38*$F$229,F38) | J38: 216 | K38: 15 | L38: =I38-J38*K38 | M38: =L38/D38 | N38: http://www.economicos.cl/propiedades/vendo-terreno-industrial-codAAU2M7Y.html | O38: terreno plano con dos galpones industriales | P38: Ref ind 2025-191103
A39: Propiedad industrial en Puerto Montt | B39: X | C39: Puerto Montt | D39: 10000 | E39: 2860347 | F39: =E39*1000/$H$2 | G39: 45980 | H39: Oferta | I39: =IF(H39="Oferta",F39*$F$229,F39) | J39: 2986 | K39: 15 | L39: =I39-J39*K39 | M39: =L39/D39 | N39: http://www.economicos.cl/propiedades/comercial-mares-de-chiloe-spa-puerto-montt-codAAUWBJA.html | O39: terreno en forma de rectángulo irregular, con un frente a la ruta, con construcciones de tipo industrial | P39: Ref ind 2025-191104
A40: Propiedad industrial en Cardonal | B40: X | C40: Puerto Montt | D40: 10600 | E40: 150000 | F40: =E40*1000/$H$2 | G40: 45771 | H40: Oferta | I40: =IF(H40="Oferta",F40*$F$229,F40) | J40: 0 | K40: 0 | L40: =I40-J40*K40 | M40: =L40/D40 | N40: http://www.economicos.cl/propiedades/oportunidad-dos-parcelas-parque-industrial-apiasmontt-codAAULS3Y.html | O40: dos parcelas, total de 10.600 m2, a 3 kilómetros de la Rotanda Cardonal, en Ruta 226 a Tepual. Existe conexión a electricidad y agua | P40: Ref ind 2025-191105
A41: Terreno en Puerto Montt | B41: X | C41: Puerto Montt | D41: 31625 | E41: =F41*$H$2/1000 | F41: 63000 | G41: 45980 | H41: Oferta | I41: =IF(H41="Oferta",F41*$F$229,F41) | J41: 0 | K41: 0 | L41: =I41-J41*K41 | M41: =L41/D41 | N41: http://www.economicos.cl/propiedades/sitio-o-terreno-en-venta-en-puerto-montt-codR77205366-5L0-5263V.html | O41: terreno de uso comercial e industrial, cin construcciones | P41: Ref ind 2025-191106
A42: Terreno en Puerto Montt | B42: X | C42: Puerto Montt | D42: 30000 | E42: =F42*$H$2/1000 | F42: 50000 | G42: 45980 | H42: Oferta | I42: =IF(H42="Oferta",F42*$F$229,F42) | J42: 0 | K42: 0 | L42: =I42-J42*K42 | M42: =L42/D42 | N42: http://www.economicos.cl/propiedades/sitio-o-terreno-en-venta-en-puerto-varas-codR77205366-5L0-27548V.html | O42: terreno plano, acceso por caletera Ruta 5 Sur, acceso a servicios básicos | P42: Ref ind 2025-191107
A43: Terreno con playa en Quemchi | B43: X | C43: Quemchi | D43: 52000 | E43: =F43*$H$2/1000 | F43: 20000 | G43: 45980 | H43: Oferta | I43: =IF(H43="Oferta",F43*$F$229,F43) | J43: 0 | K43: 0 | L43: =I43-J43*K43 | M43: =L43/D43 | N43: https://ppartnersgroup.com/es-cl/propiedad/lindo-terreno-con-orilla-de-playa-sector-arrayanes-de-huite-quemchi/66798b803bdb40e7c2d66b81/ | O43: terreno irregular, semiplano, sin habilitar con frente a borde costero | P43: Ref ind 2025-191108
A44: Terreno orilla playa | B44: X | C44: Ancud | D44: 13200 | E44: 149000 | F44: 3759 | G44: 45980 | H44: Oferta | I44: =IF(H44="Oferta",F44*$F$229,F44) | J44: 0 | K44: 0 | L44: =I44-J44*K44 | M44: =L44/D44 | N44: https://cl.portalterreno.com/propiedad/venta/terreno/ancud/318644-unico-132-ha-preciosa-vista-orilla-playa-bahia-yuste-ancud | O44: Terreno con orilla de playa, | P44: Ref ind 2025-211101
A45: Terreno orilla playa | B45: X | C45: Ancud | D45: 10000 | E45: 85000 | F45: =E45*1000/$H$2 | G45: 45980 | H45: Oferta | I45: =IF(H45="Oferta",F45*$F$229,F45) | J45: 0 | K45: 0 | L45: =I45-J45*K45 | M45: =L45/D45 | N45: https://cl.portalterreno.com/propiedad/venta/terreno/ancud/341856-preciosa-vista-y-orilla-limpio-1-ha-nal-bajo-ancud-chiloe | O45: Terreno con orilla de playa, | P45: Ref ind 2025-211102
A46: Terreno en Chonchi | B46: X | C46: Chonchi | D46: 17000 | E46: 110000 | F46: =E46*1000/$H$2 | G46: 45980 | H46: Oferta | J46: 0 | K46: 0 | L46: =IF(H46="Oferta",F46*$F$229-(J46*K46),F46) | M46: =L46/D46 | N46: https://cl.portalterreno.com/propiedad/venta/terreno/quemchi/275279-precioso-17ha-vista-paso-orilla-puerto-huite-quemchi-chiloe | O46: terreno sin habilitar, semiplano, a 600 metros de orilla de playa | P46: Ref ind 2025-211103
A47: Terreno industrial | B47: X | C47: Chonchi | D47: 10000 | E47: 222559 | F47: 5614 | G47: 45057 | H47: Oferta | I47: =IF(H47="Oferta",F47*$F$229,F47) | J47: 75 | K47: 6 | L47: =I47-J47*K47 | M47: =L47/D47 | N47: https://www.toctoc.com/propiedades/compracorredorasr/terreno/chonchi/terreno-industrial-sector-canan-chonchi/2562969?o=mapa | O47: terreno plano con casa de 75 m2 y planta de producción de hielo | P47: Ref ind 2025-281101
A48: Terreno comercial en Quemchi | B48: X | C48: Quemchi | D48: 3049 | E48: 368685 | F48: 9300 | G48: 45930 | H48: Oferta | I48: =IF(H48="Oferta",F48*$F$229,F48) | J48: 385 | K48: 6 | L48: =I48-J48*K48 | M48: =L48/D48 | N48: https://www.toctoc.com/propiedades/compracorredorasr/terreno/quemchi/16-en-quemchi/3959982 | O48: sitio en el acceso principal de Quemchi, comuna situada en el hermoso sector del Borde Costero | P48: Ref ind 2025-281102
A49: Terreno en Castro | B49: X | C49: Castro | D49: 14200 | E49: 432115 | F49: 10900 | G49: 45722 | H49: Oferta | I49: =IF(H49="Oferta",F49*$F$229,F49) | J49: 0 | K49: 0 | L49: =I49-J49*K49 | M49: =L49/D49 | N49: https://www.toctoc.com/propiedades/compracorredorasr/terreno/castro/terreno-en-venta-en-la-hermosa-localidad-de-ten-te/3509379 | O49: localidad de Ten Ten,urbanizada y con agua de vertiente, orilla del mar, cercano a centro urbano | P49: Ref ind 2025-281103
A51: Coronel | B51: VIII | C51: Coronel | D51: 289350 | E51: =F51*H2/1000 | F51: =D51*1.6 | G51: 45853 | H51: Oferta | J51: 0 | L51: =IF(H51="Oferta",F51*$F$229-(J51*K51),F51) | M51: =L51/D51 | N51: https://gpsproperty.cl/183547 | O51: PARQUE INDUSTRIAL Coronel (M-17 / B1)
A52: Coronel | B52: VIII | C52: Coronel | D52: =51453.76/1.8 | E52: =F52*H2/1000 | F52: 51453.76 | G52: 45853 | H52: Oferta | J52: 0 | L52: =IF(H52="Oferta",F52*$F$229-(J52*K52),F52) | M52: =L52/D52 | N52: https://gpsproperty.cl/183546 | O52: PARQUE INDUSTRIAL Coronel (M-17 / LT1)
A53: Coronel | B53: VIII | C53: Coronel | D53: 39312 | E53: =F53*H2/1000 | F53: 74962.8 | G53: 45853 | H53: Oferta | J53: 0 | L53: =IF(H53="Oferta",F53*$F$229-(J53*K53),F53) | M53: =L53/D53 | N53: https://gpsproperty.cl/183545 | O53: PARQUE INDUSTRIAL Coronel (M-17 / LT2)
A54: Coronel | B54: VIII | C54: Coronel | D54: 76857.33 | E54: =F54*H2/1000 | F54: 161400.39 | G54: 45853 | H54: Oferta | J54: 0 | L54: =IF(H54="Oferta",F54*$F$229-(J54*K54),F54) | M54: =L54/D54 | N54: https://gpsproperty.cl/162117 | O54: PARQUE INDUSTRIAL Coronel (M-18 / LT3)
A55: Coronel | B55: VIII | C55: Coronel | D55: 75375 | E55: =F55*H2/1000 | F55: 158287.5 | G55: 45853 | H55: Oferta | J55: 0 | L55: =IF(H55="Oferta",F55*$F$229-(J55*K55),F55) | M55: =L55/D55 | N55: https://gpsproperty.cl/183543 | O55: PARQUE INDUSTRIAL Coronel (M-18 / LT2)
A56: Coronel | B56: VIII | C56: Coronel | D56: 25648 | E56: =F56*H2/1000 | F56: 56425.6 | G56: 45853 | H56: Oferta | J56: 0 | L56: =IF(H56="Oferta",F56*$F$229-(J56*K56),F56) | M56: =L56/D56 | N56: https://gpsproperty.cl/183544 | O56: PARQUE INDUSTRIAL Coronel (M-18 / LT1)
A57: Coronel | B57: VIII | C57: Coronel | D57: 535127.75 | E57: =F57*H2/1000 | F57: 965220.5 | G57: 45853 | H57: Oferta | J57: 0 | L57: =IF(H57="Oferta",F57*$F$229-(J57*K57),F57) | M57: =L57/D57 | N57: https://gpsproperty.cl/183548 | O57: Terreno para desarrollo industrial, Con acceso a red ferroviaria y a la ruta 160.
A58: Coronel | B58: VIII | C58: Coronel | D58: 37392 | E58: =F58*H2/1000 | F58: 56088 | G58: 45731 | H58: Oferta | J58: 0 | L58: =IF(H58="Oferta",F58*$F$229-(J58*K58),F58) | M58: =L58/D58 | N58: https://inmueble.mercadolibre.cl/MLC-2854244540-gran-terreno-en-parque-industrial-escuadron-_JM#polycard_client=search-nordic&position=3&search_layout=grid&type=item&tracking_id=fdd9fd7a-b853-41cd-9288-82da0f45f9f3 | O58: permite actividades industriales de todo tipo, incluyendo aquellas que califican como PELIGROSAS. Lote urbanizado.
A59: Coronel | B59: VIII | C59: Coronel | D59: 71806.73 | E59: =F59*$H$2/1000 | F59: 107710 | G59: 45762 | H59: Oferta | J59: 0 | L59: =IF(H59="Oferta",F59*$F$229-(J59*K59),F59) | M59: =L59/D59 | N59: https://inmueble.mercadolibre.cl/MLC-2865358164-sotomayor-playa-negra-_JM#polycard_client=search-nordic&position=5&search_layout=grid&type=item&tracking_id=fdd9fd7a-b853-41cd-9288-82da0f45f9f3 | O59: Propiedad con aptitud para uso industrial y actividades productivas, emplazada al sur del puerto de Coronel, se divide en dos lotes, forma irregular y topografía mixta, principalmente ondulado.
A60: Coronel | B60: VIII | C60: Coronel | D60: 22730 | E60: =F60*$H$2/1000 | F60: 140000 | G60: 45762 | H60: Oferta | J60: 12310 | K60: 7 | L60: =IF(H60="Oferta",F60*$F$229-(J60*K60),F60) | M60: =L60/D60 | N60: https://inmueble.mercadolibre.cl/MLC-1629977973-propiedad-industrial-en-parque-industrial-coronel-_JM#polycard_client=search-nordic&position=12&search_layout=grid&type=item&tracking_id=fdd9fd7a-b853-41cd-9288-82da0f45f9f3 | O60: 514 m2 de oficinas con construcciones, 10.955 m2 de bodegas , 740 m2 de cobertizos de bodegas y 101 m2 de baños para personal
A61: Coronel | B61: VIII | C61: Coronel | D61: 172973 | E61: =F61*$H$2/1000 | F61: 345946 | G61: 45488 | H61: Oferta | J61: 0 | L61: =IF(H61="Oferta",F61*$F$229-(J61*K61),F61) | M61: =L61/D61 | N61: https://inmueble.mercadolibre.cl/MLC-1624390421-venta-de-terreno-industrial-en-coronel-id-57341-lin-_JM#polycard_client=search-nordic&position=13&search_layout=grid&type=item&tracking_id=fdd9fd7a-b853-41cd-9288-82da0f45f9f3 | O61: Con buen acceso a Ruta 160, vía ferroviaria y puerto de Coronel, en una zona de alta concentración y desarrollo industrial.
A62: Coronel | B62: VIII | C62: Coronel | D62: 23070 | E62: =F62*$H$2/1000 | F62: 50754 | G62: 45488 | H62: Oferta | J62: 0 | L62: =IF(H62="Oferta",F62*$F$229-(J62*K62),F62) | M62: =L62/D62 | N62: https://inmueble.mercadolibre.cl/MLC-1624390421-venta-de-terreno-industrial-en-coronel-id-57341-lin-_JM#polycard_client=search-nordic&position=13&search_layout=grid&type=item&tracking_id=fdd9fd7a-b853-41cd-9288-82da0f45f9f3 | O62: Con buen acceso a Ruta 160, vía ferroviaria y puerto de Coronel, en una zona de alta concentración y desarrollo industrial.
A63: Coronel | B63: VIII | C63: Coronel | D63: 76857 | E63: =F63*$H$2/1000 | F63: 192143 | G63: 45488 | H63: Oferta | J63: 0 | L63: =IF(H63="Oferta",F63*$F$229-(J63*K63),F63) | M63: =L63/D63 | N63: https://inmueble.mercadolibre.cl/MLC-1624390421-venta-de-terreno-industrial-en-coronel-id-57341-lin-_JM#polycard_client=search-nordic&position=13&search_layout=grid&type=item&tracking_id=fdd9fd7a-b853-41cd-9288-82da0f45f9f3 | O63: Con buen acceso a Ruta 160, vía ferroviaria y puerto de Coronel, en una zona de alta concentración y desarrollo industrial.
A64: Coronel | B64: VIII | C64: Coronel | D64: 5000 | E64: =F64*$H$2/1000 | F64: 13500 | G64: 45458 | H64: Oferta | J64: 0 | L64: =IF(H64="Oferta",F64*$F$229-(J64*K64),F64) | M64: =L64/D64 | N64: https://www.portalinmobiliario.com/MLC-2909219742-venta-terreno-industrial-urbanizado-con-seguridad-coronel-_JM#polycard_client=search-nordic&position=13&search_layout=grid&type=item&tracking_id=4280ceb2-f091-4d32-93c4-f6c44541e89b | O64: Zona Industrial ZAP 2, terreno plano en loteo, con conexión a servicios básicos
A65: Coronel | B65: VIII | C65: Coronel | D65: 10400 | E65: =F65*$H$2/1000 | F65: 20900 | G65: 45458 | H65: Oferta | J65: 0 | L65: =IF(H65="Oferta",F65*$F$229-(J65*K65),F65) | M65: =L65/D65 | N65: https://www.portalinmobiliario.com/MLC-2909028188-venta-terreno-industrial-urbanizado-con-seguridad-coronel-_JM#polycard_client=search-nordic&position=14&search_layout=grid&type=item&tracking_id=4280ceb2-f091-4d32-93c4-f6c44541e89b | O65: Zona Industrial ZAP 2, terreno plano en loteo, con conexión a servicios básicos
A66: Coronel | B66: VIII | C66: Coronel | D66: 20650 | E66: =F66*$H$2/1000 | F66: 41100 | G66: 45458 | H66: Oferta | J66: 0 | L66: =IF(H66="Oferta",F66*$F$229-(J66*K66),F66) | M66: =L66/D66 | N66: https://www.portalinmobiliario.com/MLC-2909067236-venta-terreno-industrial-urbanizado-con-seguridad-coronel-_JM#polycard_client=search-nordic&position=15&search_layout=grid&type=item&tracking_id=47848bb3-5694-47e0-9ad0-8030963371a5 | O66: Zona Industrial ZAP 2, terreno plano en loteo, con conexión a servicios básicos
A67: Coronel | B67: VIII | C67: Coronel | D67: 10200 | E67: =F67*$H$2/1000 | F67: 21700 | G67: 45458 | H67: Oferta | J67: 0 | L67: =IF(H67="Oferta",F67*$F$229-(J67*K67),F67) | M67: =L67/D67 | N67: https://www.portalinmobiliario.com/MLC-2908969822-venta-terreno-industrial-urbanizado-con-seguridad-coronel-_JM#polycard_client=search-nordic&position=17&search_layout=grid&type=item&tracking_id=47848bb3-5694-47e0-9ad0-8030963371a5 | O67: Zona Industrial ZAP 2, terreno plano en loteo, con conexión a servicios básicos
A68: Coronel | B68: VIII | C68: Coronel | D68: 30400 | E68: =F68*$H$2/1000 | F68: 59100 | G68: 45458 | H68: Oferta | J68: 0 | L68: =IF(H68="Oferta",F68*$F$229-(J68*K68),F68) | M68: =L68/D68 | N68: https://www.portalinmobiliario.com/MLC-2908981676-venta-terreno-industrial-urbanizado-con-seguridad-coronel-_JM#polycard_client=search-nordic&position=18&search_layout=grid&type=item&tracking_id=47848bb3-5694-47e0-9ad0-8030963371a5 | O68: Zona Industrial ZAP 2, terreno plano en loteo, con conexión a servicios básicos
A69: Coronel | B69: VIII | C69: Coronel | D69: 4034 | E69: =D69*102000/1000 | F69: =E69*1000/H2 | G69: 45841 | H69: Oferta | J69: 0 | L69: =IF(H69="Oferta",F69*$F$229-(J69*K69),F69) | M69: =L69/D69 | N69: https://inmueble.mercadolibre.cl/MLC-2950192980-terreno-parque-industrial-coronel-_JM#polycard_client=search-nordic&position=14&search_layout=grid&type=item&tracking_id=fdd9fd7a-b853-41cd-9288-82da0f45f9f3 | O69: Terreno Parque Industrial de 4.034 m2 con acceso expeditos
A70: Tomé | B70: VIII | C70: Tomé | D70: 5046 | E70: 772001 | F70: 19679 | G70: 45488 | H70: Oferta | J70: 0 | L70: =IF(H70="Oferta",F70*$F$229-(J70*K70),F70) | M70: =L70/D70 | N70: https://inmueble.mercadolibre.cl/MLC-1539847587-venta-de-terreno-en-tome-id-51987-lin-_JM#polycard_client=search-nordic&position=9&search_layout=grid&type=item&tracking_id=4712fe89-22cd-456f-80ca-5ca931519580 | O70: Uso residencial y equpamiento. Normativa: Coeficiente ocupación de suelo: 40% Coeficiente Constructibilidad 0,8. Densidad bruta: 100 hab/ha.
A71: Tomé | B71: VIII | C71: Tomé | D71: 4445 | E71: 627675 | F71: 16000 | G71: 45488 | H71: Oferta | J71: 0 | L71: =IF(H71="Oferta",F71*$F$229-(J71*K71),F71) | M71: =L71/D71 | N71: https://inmueble.mercadolibre.cl/MLC-2749335096-venta-de-terreno-en-tome-id-51986-lin-_JM#polycard_client=search-nordic&position=8&search_layout=grid&type=item&tracking_id=4712fe89-22cd-456f-80ca-5ca931519580 | O71: Uso residencial y equpamiento. Normativa: Coeficiente ocupación de suelo: 40% Coeficiente Constructibilidad 0,8. Densidad bruta: 100 hab/ha.
A72: Tomé | B72: VIII | C72: Tomé | D72: 3680 | E72: 461969 | F72: 11776 | G72: 45488 | H72: Oferta | J72: 0 | L72: =IF(H72="Oferta",F72*$F$229-(J72*K72),F72) | M72: =L72/D72 | N72: https://inmueble.mercadolibre.cl/MLC-1539886823-venta-de-terreno-en-tome-id-51985-lin-_JM#polycard_client=search-nordic&position=10&search_layout=grid&type=item&tracking_id=4712fe89-22cd-456f-80ca-5ca931519580 | O72: Uso residencial y equpamiento. Normativa: Coeficiente ocupación de suelo: 40% Coeficiente Constructibilidad 0,8. Densidad bruta: 100 hab/ha.
A73: Tomé | B73: VIII | C73: Tomé | D73: 12006 | E73: 460000 | F73: =E73*1000/$H$2 | G73: 45488 | H73: Oferta | J73: 0 | L73: =IF(H73="Oferta",F73*$F$229-(J73*K73),F73) | M73: =L73/D73 | N73: https://inmueble.mercadolibre.cl/MLC-2833251920-terreno-cementerio-2-loma-larga-tome-_JM#polycard_client=search-nordic&position=3&search_layout=grid&type=item&tracking_id=4712fe89-22cd-456f-80ca-5ca931519580 | O73: acceso por Calle Ñipas 937 Tomé, terreno regular con pendiente.
A74: Tomé | B74: VIII | C74: Tomé | D74: 10000 | E74: 375192 | F74: =E74*1000/$H$2 | G74: 45853 | H74: Oferta | J74: 0 | L74: =IF(H74="Oferta",F74*$F$229-(J74*K74),F74) | M74: =L74/D74 | N74: https://casas.trovit.cl/detail/trovit-CL-6030016702062535590?type=traffic | O74: terreno urbano, sin construcciones
A75: Valdivia | B75: XIV | C75: Valdivia | D75: 1295 | E75: =F75*H2/1000 | F75: 15540 | G75: 45249 | H75: Oferta | L75: =IF(H75="Oferta",F75*$F$229-(J75*K75),F75) | M75: =L75/D75 | N75: https://inmueble.mercadolibre.cl/MLC-2109825626-excelente-terreno-en-avenida-ramon-picarte-_JM#position=1&search_layout=map&type=item&tracking_id=20e8a088-d21f-4f02-b15e-1278d1e8e7c4 | O75: Avenida Ramon Picarte y como referente frente al Cementerio General.
A76: Valdivia | B76: XIV | C76: Valdivia | D76: 2697.2 | E76: =F76*H2/1000 | F76: 37000 | G76: 45127 | H76: Oferta | L76: =IF(H76="Oferta",F76*$F$229-(J76*K76),F76) | M76: =L76/D76 | N76: https://inmueble.mercadolibre.cl/MLC-1399277865-av-ramon-picarte-galvez-_JM#position=1&search_layout=map&type=item&tracking_id=a2dfe491-5b04-4653-8c77-1b6b58536368 | O76: Cuenta con excelente conectividad y accesibilidad, frente a Av. Ramón Picarte y a 700 metros de Av. Pedro Montt, que comunica directamente con la Ruta 5 Sur y con el resto del país. Superficie construida: 674 m2.
A77: Valdivia | B77: XIV | C77: Valdivia | D77: 9452 | E77: =F77*H2/1000 | F77: 30500 | G77: 45248 | H77: Oferta | L77: =IF(H77="Oferta",F77*$F$229-(J77*K77),F77) | M77: =L77/D77 | N77: https://inmueble.mercadolibre.cl/MLC-1441385517-gran-terreno-en-venta-calle-arica-valdivia-_JM#position=1&search_layout=map&type=item&tracking_id=a3709776-794c-4113-920b-f963542ff602 | O77: ubicada en calle Arica, Valdivia. Sector Industrial, en crecimiento muy cercano a Circunvalación Sur, Puerto las Mulatas, Campus Miraflores de la UACH entre otros rubros como comercio y actividades portuarias y de navegación. Terreno urbano apto para uso industrial, almacenamiento y vivienda.
A78: Valdivia | B78: XIV | C78: Valdivia | D78: 9500 | E78: =F78*H2/1000 | F78: 46550 | G78: 45158 | H78: Oferta | L78: =IF(H78="Oferta",F78*$F$229-(J78*K78),F78) | M78: =L78/D78 | N78: https://www.portalinmobiliario.com/MLC-1819205040-industrial-en-venta-en-valdivia-_JM#position=9&search_layout=map&type=item&tracking_id=a72dc94e-1e1b-4fe3-98bc-a2b99e16111b | O78: 9500 m2 apto para industrias molesta e inofensiva, equipamiento, habitacional, ubicado a 3 kilómetros al centro de la ciudad de Valdivia. Ideal para desarrollo de bodegas para renta.
A79: Valdivia | B79: XIV | C79: Valdivia | D79: 5000 | E79: =F79*H2/1000 | F79: 6400 | G79: 45244 | H79: Oferta | L79: =IF(H79="Oferta",F79*$F$229-(J79*K79),F79) | M79: =L79/D79 | N79: https://www.portalinmobiliario.com/MLC-2099788546-venta-directa-terreno-comercial-5000-m2-y-galpon-nuevo-_JM#position=5&search_layout=map&type=item&tracking_id=ba2d3f8b-098a-41b9-b2e5-097ea9207138 | O79: terreno y galpón en el sector industrial de Llancahue, salida sur de Valdivia. El terreno de 5.000 m² es totalmente plano y aprovechable, parcialmente cerrado con cerco metálico. La propiedad incluye un galpón nuevo de 204 m² con 2 contenedores de 40 pies cerrados y una zona de trabajo de 75 m². Ubicación estratégica con acceso desde Av. Picarte y salida sur de Valdivia
A80: Valdivia | B80: XIV | C80: Valdivia | D80: 2900 | E80: =F80*H2/1000 | F80: 36000 | G80: 45127 | H80: Oferta | L80: =IF(H80="Oferta",F80*$F$229-(J80*K80),F80) | M80: =L80/D80 | N80: https://inmueble.mercadolibre.cl/MLC-1405159205-picarte-2900-mt2-cercano-av-francia-valdivia-36000-uf-_JM#position=2&search_layout=map&type=item&tracking_id=a3954309-c5f9-4752-acc9-a8e83abfed34 | O80: Propiedad ubicada en pleno eje picarte, en dirección sur, a la altura del 2700, en la ciudad de Valdivia. Zona ZU-4 Vivienda.Equipamiento de los tipo y escala.Industria, almacenamiento y talleres inofensivos.Actividades complementarias a la vialidad y al transporte.
A81: Valdivia | B81: XIV | C81: Valdivia | D81: 3075 | E81: =F81*H2/1000 | F81: =D81*12 | G81: 45127 | H81: Oferta | L81: =IF(H81="Oferta",F81*$F$229-(J81*K81),F81) | M81: =L81/D81 | N81: https://inmueble.mercadolibre.cl/MLC-1815258680-terreno-avenida-ecuador-12-uf-m-_JM#position=4&search_layout=map&type=item&tracking_id=cad76cb3-23f0-49f4-af5c-fbad5843aae2 | O81: ompuesta de tres lotes, ubicada en pleno proyecto de Barrio Cívico de la ciudad donde termina la ampliación a la Avenida Costanera, calle de gran tráfico que conecta la ciudad con Sector Collico, Corvi, Ciudad de los Lagos, desde este terreno se puede conectar fácilmente a todos los puntos de la ciudad
A82: Valdivia | B82: XIV | C82: Valdivia | D82: 5000 | E82: =F82*H2/1000 | F82: 3560 | G82: 44157 | H82: Oferta | L82: =IF(H82="Oferta",F82*$F$229-(J82*K82),F82) | M82: =L82/D82 | N82: https://www.economicos.cl/propiedades/vendo-terreno-industrial-en-valdivia-codAAREWBQ.html | O82: Terreno eriazo. sector Industrial de Valdivia, sector Sevilla, ubicado en las Animas, entre puente Cau-Cau y Puente Calle Calle. Excelente terreno para instalación de industria o galpones. Postes de linea de media tensión y agua potable
A83: Caldera | B83: III | C83: Copiapo | D83: 3337 | E83: =F83*H2/1000 | F83: 3000 | G83: 45250 | H83: Oferta | L83: =IF(H83="Oferta",F83*$F$229-(J83*K83),F83) | M83: =L83/D83 | N83: https://casas.mitula.cl/adform/24301-256-32da-42ed8cb7b2e3-9730-da432e1d-2647?page=1&pos=1&t_sec=1&t_or=2&t_pvid=bcf36153-1665-47f3-92f6-2c3da16c8c89&req_sgmt=REVTS1RPUDtTRU87U0VSUDs%3D | O83: Caldera, Terreno En Venta En Barrio Industrial Caldera
A84: Caldera | B84: III | C84: Copiapo | D84: 26908 | E84: =F84*H2/1000 | F84: 29599 | G84: 45066 | H84: Oferta | L84: =IF(H84="Oferta",F84*$F$229-(J84*K84),F84) | M84: =L84/D84 | N84: https://inmueble.mercadolibre.cl/MLC-1681083432-increible-oportunidad-de-inversion-para-proyectos-en-caldera-_JM#position=1&search_layout=map&type=item&tracking_id=ae3f3235-8f24-491f-8b39-e9708c7b39a6 | O84: Terreno en el acceso norte de Caldera, en un barrio industrial de alta demanda. Su ubicación estratégica asegura fácil acceso a principales vías y servicios públicos. Parcelado en 12 lotes, ofrece la opción de venta individual o desarrollo de proyectos independientes, brindando flexibilidad y diversas oportunidades de inversión.
A85: Caldera | B85: III | C85: Copiapo | D85: 1250 | E85: =F85*H2/1000 | F85: 9640 | G85: 45222 | H85: Oferta | L85: =IF(H85="Oferta",F85*$F$229-(J85*K85),F85) | M85: =L85/D85 | N85: https://inmueble.mercadolibre.cl/MLC-2060222502-venta-terreno-barrio-industrial-caldera-_JM#position=11&search_layout=map&type=item&tracking_id=6ed2e9a0-70b1-4d50-bf77-72794990f88a | O85: zona industrial, caldera
A86: Talcahuano | B86: VIII | C86: Talcahuano | D86: 355134 | E86: =F86*H2/1000 | F86: 360000 | G86: 45852 | H86: Oferta | J86: 903 | K86: 8 | L86: =IF(H86="Oferta",F86*$F$229-(J86*K86),F86) | M86: =L86/D86 | N86: https://gpsproperty.cl/184353 | O86: 903m2 oficinas, Terreno Industrial de forma irregular, con topografía mixta, ubicado en zona industrial de Talcahuano.
A87: Talcahuano | B87: VIII | C87: Talcahuano | D87: 400000 | E87: =F87*H2/1000 | F87: 800000 | G87: 45852 | H87: Oferta | J87: 0 | L87: =IF(H87="Oferta",F87*$F$229-(J87*K87),F87) | M87: =L87/D87 | N87: https://gpsproperty.cl/161620 | O87: Emplazado al costado Poniente del Aeropuerto Carriel Sur, a 2,5 kilómetros de distancia del acceso a la Autopista Concepción-Talcahuano
A88: Av. Michaihue Ruta 160 | B88: VIII | C88: San Pedro de La Paz | D88: 45776.3 | E88: =F88*$H$2/1000 | F88: 142241 | G88: 45852 | H88: Oferta | J88: 0 | L88: =IF(H88="Oferta",F88*$F$229-(J88*K88),F88) | M88: =L88/D88 | N88: https://gpsproperty.cl/162327 | O88: Ubicado en Zona ZI-1, terreno esquina con frente hacia avenida Michaihue y Ruta 160, uso comercial e industrial.
A89: Carriel | B89: XIV | C89: Talcahuano | D89: 2219 | E89: =F89*H2/1000 | F89: 15265 | G89: 45240 | H89: Oferta | L89: =IF(H89="Oferta",F89*$F$229-(J89*K89),F89) | M89: =L89/D89 | N89: https://inmueble.mercadolibre.cl/MLC-1439012201-terreno-construccion-en-venta-en-talcahuano-_JM#position=3&search_layout=map&type=item&tracking_id=a7c480dc-d320-406b-a6aa-5e703b335914 | O89: Construcción de 556 m2.. Sitio con topografía semiplano en zona residencial mixta de la comuna de Talcahuano con una ubicación privilegiada a pasos de la plaza de armas de la comuna y a la Ilustre Municipalidad de Talcahuano.
A90: Bodega industrial en San Vicente | B90: VIII | C90: Talcahuano | D90: 14060 | E90: 3670159 | F90: 93000 | G90: 45852 | H90: Oferta | J90: 8264 | K90: 6 | L90: =IF(H90="Oferta",F90*$F$229-(J90*K90),F90) | M90: =L90/D90 | N90: https://www.portalinmobiliario.com/MLC-2877727398-industrial-en-venta-en-talcahuano-_JM#polycard_client=search-nordic&position=1&search_layout=grid&type=item&tracking_id=02ae84c5-1fd1-4be2-8269-e4f0646eeb81 | O90: Tipo zona: ZI-4. Usos permitidos: Actividades Productivas de Industria,taller y establecimientos de bodegaje inofensivo y molesto.
A91: Lote 1, Av Las Golondrinas Dinahue | B91: VIII | C91: Talcahuano | D91: 13813.1 | E91: =F91*$H$2/1000 | F91: 69066 | G91: 45852 | H91: Oferta | J91: 0 | L91: =IF(H91="Oferta",F91*$F$229-(J91*K91),F91) | M91: =L91/D91 | N91: https://gpsproperty.cl/185659 | O91: actualmente es usado como estacionamiento de camiones. Cuenta con 7 oficinas en contenedores no anclados al piso.
A92: Lote 2, Av Las Golondrinas Dinahue | B92: VIII | C92: Talcahuano | D92: 8533 | E92: =F92*$H$2/1000 | F92: 38400 | G92: 45852 | H92: Oferta | J92: 0 | L92: =IF(H92="Oferta",F92*$F$229-(J92*K92),F92) | M92: =L92/D92 | N92: https://gpsproperty.cl/185660 | O92: Con frente hacia Dinahue, en estado natural, con vegetación baja, posee forma regular y topografías suave.
A96: Terreno insdustrial Castro | B96: X | C96: Castro | D96: 16800 | E96: =F96*H2/1000 | F96: 84000 | G96: 44877 | H96: Oferta | L96: =IF(H96="Oferta",F96*$F$229-(J96*K96),F96) | M96: =L96/D96 | N96: http://www.economicos.cl/propiedades/propiedad-industrial-en-venta-en-castro-codR76244956-0L0-21583.html | O96: Terreno Industrial y urbano con más de 60 m de frente a la ruta 5 sur, muy cerca de la estación Petrobrás, frente al cruce a Dalcahue, en estrátegica ubicación en el sector industrial de la entrada norte de Castro. Agua por APR y empalme eléctrico con capacidad trifácica.
A97: Terreno insdustrial Chonchi | B97: X | C97: Chonchi | D97: =22.5*10000 | E97: =1214974250/1000 | F97: 35000 | G97: 44450 | H97: Oferta | L97: =IF(H97="Oferta",F97*$F$229-(J97*K97),F97) | M97: =L97/D97 | N97: https://www.portalterreno.com/cl/propiedad/venta/industrial/chonchi/178491-quinched-chonchi | O97: acceso por ruta W-591, con 4.029 m2 construidos,
A98: Terreno industrial, mismo sector tasado | B98: X | C98: Chonchi | D98: 12254 | E98: 600000 | F98: =E98*1000/H2 | G98: 44870 | H98: Oferta | L98: =IF(H98="Oferta",F98*$F$229-(J98*K98),F98) | M98: =L98/D98 | N98: https://www.portalinmobiliario.com/MLC-1135732957-industrial-en-venta-en-chonchi-_JM#position=1&search_layout=stack&type=item&tracking_id=784387b2-38ff-4346-ab27-90801626eae8 | O98: con construcción en mal estado por incendio, acceso por Ruta W-853, mismo sector tasado, en zona Zex-1( Vivienda y Equipamiento ).
A99: Propiedad en Chonchi | B99: X | C99: Chonchi | D99: 10000 | E99: =185703611/1000 | F99: 5364 | G99: 44847 | H99: Oferta | L99: =IF(H99="Oferta",F99*$F$229-(J99*K99),F99) | M99: =L99/D99 | N99: https://www.toctoc.com/propiedades/compracorredorasr/terreno/chonchi/hermoso-terreno-con-excelente-vista-al-mar/2209480?o=resultado_lista_seo_img | O99: Suelos planos, primera linea frente al mar , en altura, con serviciós básicos de APR y tendido eléctrico
A100: Terreno urbano en Castro | B100: X | C100: Castro | D100: 16200 | E100: 500000 | F100: 14403.6 | G100: 44875 | H100: Oferta | L100: =IF(H100="Oferta",F100*$F$229-(J100*K100),F100) | M100: =L100/D100 | N100: http://www.terrenochiloe.cl/propiedad/excelente-oportunidad-de-inversion-4 | O100: Terreno ubicado en sector cruce Llau.-Llao comuna de Castro, terreno orilla de carretera, camino hacia Putemun y entrada de Castro, sector de alta plusvalía.
A101: Tereno habitacional | B101: X | C101: Chonchi | D101: 170000 | E101: 765000 | F101: 29034 | G101: 44875 | H101: Oferta | L101: =IF(H101="Oferta",F101*$F$229-(J101*K101),F101) | M101: =L101/D101 | N101: https://chile.buscainmobiliarias.com/terreno-habitacional_en_venta_en_chiloe_i1531391.asp?utm_source=Lifull-connect&utm_medium=referrer | O101: Terreno habitacional, sin habilitar, Chonchi
A102: Tereno en Quillota | B102: V | C102: Quillota | D102: 20000 | E102: 581143 | F102: =E102*1000/$H$2 | G102: 44169 | H102: Oferta | L102: =IF(H102="Oferta",F102*$F$229-(J102*K102),F102) | M102: =L102/D102 | N102: http://www.economicos.cl/propiedades/se-vende-terreno-con-excelente-ubicacion-en-quillota-codAARPIJA.html | O102: 2 ha planas, sin habilitar, con cultivos, cercano a hospital biprovincial
A103: Tereno en Quillota | B103: V | C103: Quillota | D103: 57000 | E103: 4728102 | F103: =E103*1000/H2 | G103: 44350 | H103: Oferta | L103: =IF(H103="Oferta",F103*$F$229-(J103*K103),F103) | M103: =L103/D103 | N103: http://www.economicos.cl/propiedades/sitio-o-terreno-en-venta-en-quillota-codR76430403-9L0-4448798.html | O103: Zona de equipamiento, cercana a centros comerciales, sin habilitar
A104: Tereno en Quillota | B104: V | C104: Quillota | D104: 11300 | E104: 669525 | F104: =E104*1000/H2 | G104: 44350 | H104: Oferta | L104: =IF(H104="Oferta",F104*$F$229-(J104*K104),F104) | M104: =L104/D104 | N104: http://www.economicos.cl/propiedades/sitio-o-terreno-en-venta-en-quillota-codR76917568-7L0-116011140.html | O104: Terreno plano, sin habilitar ubicado a las afueras del centro urbano de Quillota
A105: Terreno en sector La Tetera | B105: V | C105: Quillota | D105: 5361 | E105: 70000 | F105: =E105*1000/H2 | G105: 44050 | H105: Oferta | L105: =IF(H105="Oferta",F105*$F$229-(J105*K105),F105) | M105: =L105/D105 | N105: http://www.economicos.cl/propiedades/vendo-terreno-de-5361-m2-en-la-tetera-quillota-codAAQ7ZLA.html | O105: Terreno en sector La Tetera, area rural de la comuna, con factibilidad de servicios básicos
A106: Sitio en La Palma | B106: V | C106: Quillota | D106: 625 | E106: 22973 | F106: =E106*1000/H2 | G106: 43979 | H106: Oferta | L106: =IF(H106="Oferta",F106*$F$229-(J106*K106),F106) | M106: =L106/D106 | N106: http://www.economicos.cl/propiedades/sitio-la-palma-quillota-codAAQWXEY.html | O106: Sitio en sector La Palma
A107: Ruta 5 Norte | B107: V | C107: Hijuelas | D107: 16000 | E107: =F107*H2/1000 | F107: 12188 | G107: 44221 | H107: Oferta | L107: =IF(H107="Oferta",F107*$F$229-(J107*K107),F107) | M107: =L107/D107 | N107: http://www.ewilde.cl/propiedad/parcela-a-orilla-de-carretera-5-norte-hijuelas-/507 | O107: Orilla de Ruta 5 Norte, casa de 148 m2 en regular estado.
...

Sheet REF. Canal 
A2: REFERENCIAS DE MERCADO DERECHOS DE AGUA | J2: UF: | K2: =PORTADA!$H$8
A5: Región | B5: Comuna | C5: Sub-Cuenca | D5: Fuente | E5: Nombre de la Fuente | F5: Derechos | G5: Tipo | H5: Q Nominal L/s | I5: Valor Total M$ | J5: Valor Unit. M$/(L/s) | K5: Valor UF/(L/s) | L5: Valor Unit. Ajustado M$/L/s | M5: Fecha / Año | N5: Tipo de Referencia | O5: Link oferta o datos compraventa (fs/nº/año/CBR)
A6: V | B6: Catemu | C6: Río Aconcagua | D6: Estero | E6: Catemu | F6: 20 | G6: L/s | H6: 20 | I6: =J6*H6 | J6: =7000 | K6: =J6*1000/$K$2 | L6: =IF(N6="Oferta",J6*$D$60,J6) | M6: 45642 | N6: Oferta | O6: https://gesaguas.cl/derecho/19
A7: V | B7: Rinconada | C7: 1a seccción Río Aconcagua | D7: Canal | E7: San Miguel | F7: 5 | G7: acción | H7: 8 | I7: 64000 | J7: 8000 | K7: =J7*1000/K2 | L7: =IF(N7="Oferta",J7*$D$60,J7) | M7: 45767 | N7: Oferta | O7: https://gesaguas.cl/derecho/184
A8: V | B8: LLay Llay | C8: Río Aconcagua | D8: Canal | E8: Ucuquer | F8: 0.5 | G8: acción | H8: =F8 | I8: 1000 | J8: =I8/F8 | K8: =J8*1000/$K$2 | L8: =IF(N8="Oferta",J8*$D$60,J8) | M8: 45309 | N8: Venta | O8: fojas 28v nº 28del año 2024 CBR Llay Llay
A9: V | B9: Hijuelas | C9: Río Aconcagua | D9: Canal | E9: Purehue | F9: 43 | G9: acción | H9: =260/159.25*F9 | I9: 215000 | J9: =I9/H9 | K9: =J9*1000/$K$2 | L9: =IF(N9="Oferta",J9*$D$60,J9) | M9: 45428 | N9: Venta | O9: fojas 111v nº 96 del año 2024CBR Llay Llay
A10: V | B10: Hijuelas | C10: Río Aconcagua | D10: Canal | E10: La Sombra | F10: 12 | G10: acción | H10: =1000/390.09*F10 | I10: 60000 | J10: =I10/H10 | K10: =J10*1000/$K$2 | L10: =IF(N10="Oferta",J10*$D$60,J10) | M10: 45428 | N10: Venta | O10: fojas 113 nº 97 del año 2024CBR Llay Llay
A11: V | B11: Hijuelas | C11: Río Aconcagua | D11: Canal | E11: Ocoa | F11: 0.3 | G11: acción | H11: =736/800*F11 | I11: 1000 | J11: =I11/H11 | K11: =J11*1000/$K$2 | L11: =IF(N11="Oferta",J11*$D$60,J11) | M11: 45530 | N11: Venta | O11: fojas 190 v nº 165 del año 2024 CBR Llay Llay
A12: V | B12: Llay Llay | C12: Río Aconcagua | D12: Canal | E12: Canal del Bajo | F12: 12.54 | G12: acción | H12: 53.5 | I12: 200000 | J12: =I12/H12 | K12: =J12*1000/$K$2 | L12: =IF(N12="Oferta",J12*$D$60,J12) | M12: 44701 | N12: Venta | O12: 147/140/2022/CBR Llay Llay
A13: V | B13: Catemu | C13: 2ª sección río Aconcagua | D13: Canal | E13: Comunero o Ucuquer | F13: 12 | G13: acción | H13: 12 | I13: 88320 | J13: =I13/H13 | K13: =J13*1000/$K$2 | L13: =IF(N13="Oferta",J13*$D$60,J13) | M13: 45642 | N13: Oferta | O13: https://www.aguacircular.cl/00618-054-05
A14: V | B14: Catemu | C14: 2ª sección río Aconcagua | D14: Canal | E14: Valdesano | F14: 300 | G14: acción | H14: 9.88 | I14: 73065 | J14: =I14/H14 | K14: =J14*1000/$K$2 | L14: =IF(N14="Oferta",J14*$D$60,J14) | M14: 45642 | N14: Oferta | O14: https://www.aguacircular.cl/00619-054-05
A15: V | B15: Catemu | C15: 2ª sección río Aconcagua | D15: Canal | E15: Las Vegas Molino | F15: 2.28 | G15: acción | H15: 15.64 | I15: 86024 | J15: =I15/H15 | K15: =J15*1000/$K$2 | L15: =IF(N15="Oferta",J15*$D$60,J15) | M15: 45642 | N15: Oferta | O15: https://www.aguacircular.cl/01116-054-05
A16: V | B16: San Esteban | C16: 1ª sección Río Aconcagua | D16: Canal | E16: San Miguel | F16: 5.706 | G16: acción | H16: 10.27 | I16: 82160 | J16: =I16/H16 | K16: =J16*1000/$K$2 | L16: =IF(N16="Oferta",J16*$D$60,J16) | M16: 45642 | N16: Oferta | O16: https://www.aguacircular.cl/00098-054-05
A17: V | B17: La Calera | C17: 3ª sección Río Aconcagua | D17: Canal | E17: Waddington | F17: 20 | G17: acción | H17: =F17 | I17: 117551 | J17: =I17/H17 | K17: =J17*1000/$K$2 | L17: =IF(N17="Oferta",J17*$D$60,J17) | M17: 45642 | N17: Oferta | O17: https://www.aguacircular.cl/00647-054-05
A18: V | B18: La Calera | C18: 3ª sección Río Aconcagua | D18: Canal | E18: Waddington | F18: 2.9 | G18: acción | H18: =F18 | I18: 28938 | J18: =I18/H18 | K18: =J18*1000/$K$2 | L18: =IF(N18="Oferta",J18*$D$60,J18) | M18: 45642 | N18: Oferta | O18: https://www.aguacircular.cl/00332-054-05
A19: V | B19: Quillota | C19: 3ª sección Río Aconcagua | D19: Canal | E19: Comunidad Quillota y Candelaria | F19: 9 | G19: acción | H19: =F19*2.57 | I19: 61851 | J19: =I19/H19 | K19: =J19*1000/$K$2 | L19: =IF(N19="Oferta",J19*$D$60,J19) | M19: 45642 | N19: Oferta | O19: https://www.aguacircular.cl/00633-054-05
A20: V | B20: Quillota | C20: Río Aconcagua | D20: Canal | E20: Candelaria | F20: 0.5046 | G20: acción | H20: 0.5046 | I20: 2000 | J20: 3963.5355 | K20: 122.48751 | L20: =IF(N20="Oferta",J20*$D$60,J20) | M20: 43881 | N20: Venta | O20: 57 / 49 / 2020/ CBR Quillota
A21: V | B21: Quillota | C21: Río Aconcagua | D21: Canal | E21: Tambor | F21: 0.5 | G21: acción | H21: 0.5 | I21: 1528.038 | J21: 3056.076 | K21: 108 | L21: =IF(N21="Oferta",J21*$D$60,J21) | M21: 43882 | N21: Venta | O21: 58 / 51 / 2020/ CBR Quillota
A22: V | B22: Los Andes | C22: 1ª sección Río Aconcagua | D22: Canal | E22: Rinconada | F22: 5.538 | G22: acción | H22: 9.9684 | I22: 69778.8 | J22: 7000 | K22: =J22*1000/$K$2 | L22: =IF(N22="Oferta",J22*$D$60,J22) | M22: 45370 | N22: Venta | O22: fojas 92v nº 109 del año 2024 CBR Los Andes
A23: V | B23: Los Andes | C23: 1ª sección Río Aconcagua | D23: Canal | E23: Rinconada | F23: 3.842 | G23: acción | H23: 6.9156 | I23: 48419.37 | J23: =I23/H23 | K23: =J23*1000/$K$2 | L23: =IF(N23="Oferta",J23*$D$60,J23) | M23: 45370 | N23: Venta | O23: fojas 93v nº 111 del año 2024 CBR Los Andes
A24: V | B24: Los Andes | C24: 1ª sección Río Aconcagua | D24: Canal | E24: Rinconada | F24: 5.517 | G24: acción | H24: 9.9306 | I24: 69521.7 | J24: =I24/H24 | K24: =J24*1000/$K$2 | L24: =IF(N24="Oferta",J24*$D$60,J24) | M24: 45370 | N24: Venta | O24: fojas 91 v nº 109 del año 2024 CBR Los Andes
A25: V | B25: Los Andes | C25: 1ª sección Río Aconcagua | D25: Canal | E25: San Miguel | F25: 5 | G25: acción | H25: 8 | I25: 64000 | J25: =I25/H25 | K25: =J25*1000/$K$2 | L25: =IF(N25="Oferta",J25*$D$60,J25) | M25: 45767 | N25: Oferta | O25: https://www.aguacircular.cl/01327-054-05
A26: V | B26: Los Andes | C26: 1ª sección Río Aconcagua | D26: Canal | E26: San Miguel | F26: 10.27 | G26: L/s | H26: 10.27 | I26: 82160 | J26: =I26/H26 | K26: =J26*1000/$K$2 | L26: =IF(N26="Oferta",J26*$D$60,J26) | M26: 45767 | N26: Oferta | O26: https://www.aguacircular.cl/00098-054-05
A27: V | B27: Catemu | C27: 2ª sección río Aconcagua | D27: Canal | E27: Comunero o Ucuquer | F27: 12 | G27: acción | H27: 12 | I27: 89817 | J27: =I27/H27 | K27: =J27*1000/$K$2 | L27: =IF(N27="Oferta",J27*$D$60,J27) | M27: 45767 | N27: Oferta | O27: https://www.aguacircular.cl/00618-054-05
A28: V | B28: Catemu | C28: 2ª sección río Aconcagua | D28: Canal | E28: Valdesano | F28: 300 | G28: acción | H28: 9.88 | I28: 74303 | J28: =I28/H28 | K28: =J28*1000/$K$2 | L28: =IF(N28="Oferta",J28*$D$60,J28) | M28: 45767 | N28: Oferta | O28: https://www.aguacircular.cl/00619-054-05
A29: V | B29: Los Andes | C29: Río Aconcagua | D29: Pozo | E29: sin nombre | F29: 1 | G29: L/s | H29: =+F29 | I29: 7000 | J29: =I29/H29 | K29: =J29*1000/$K$2 | L29: =IF(N29="Oferta",J29*$D$60,J29) | M29: 43717 | N29: Venta | O29: 174 / 230 / 2019 / Los Andes
A30: V | B30: Los Andes | C30: Río Aconcagua | D30: Canal | E30: Rinconada | F30: 0.25 | G30: acción | H30: 0.45 | I30: 1250 | J30: =I30/H30 | K30: =J30*1000/$K$2 | L30: =IF(N30="Oferta",J30*$D$60,J30) | M30: 43691 | N30: Venta | O30: 159 v / 210 / 2019/ Los Andes
A31: V | B31: Los Andes | C31: Río Aconcagua | D31: Canal | E31: Quilpué | F31: 0.267 | G31: acción | H31: =F31*1.8 | I31: 1000 | J31: =I31/H31 | K31: =J31*1000/$K$2 | L31: =IF(N31="Oferta",J31*$D$60,J31) | M31: 43651 | N31: Venta | O31: 128 v / 166 / 2019 / Los Andes
A32: V | B32: Los Andes | C32: Río Aconcagua | D32: Canal | E32: San Miguel | F32: 3.5 | G32: acción | H32: =F32*1.8 | I32: 32000 | J32: =I32/H32 | K32: =J32*1000/$K$2 | L32: =IF(N32="Oferta",J32*$D$60,J32) | M32: 43633 | N32: Venta | O32: 113 v / 148 / 2019 / Los Andes
A33: V | B33: Los Andes | C33: Río Aconcagua | D33: Canal | E33: San Rafael | F33: 0.655 | G33: acción | H33: =F33*1.8 | I33: 9650 | J33: =I33/H33 | K33: =J33*1000/$K$2 | L33: =IF(N33="Oferta",J33*$D$60,J33) | M33: 43612 | N33: Venta | O33: 108 / 140 / 2019 / Los Andes
A34: V | B34: Los Andes | C34: Estero Quilpué | D34: Canal | E34: El Monte | F34: 2.88 | G34: acción | H34: 2.88 | I34: 9741 | J34: =I34/H34 | K34: =J34*1000/$K$2 | L34: =IF(N34="Oferta",J34*$D$60,J34) | M34: 43553 | N34: Venta | O34: 58 / 66 / 2019 / Los Andes
A35: V | B35: Los Andes | C35: Río Aconcagua | D35: Canal | E35: Los Cantos | F35: 32 | G35: acción | H35: 40.92 | I35: 154674 | J35: =I35/H35 | K35: =J35*1000/$K$2 | L35: =IF(N35="Oferta",J35*$D$60,J35) | M35: 43480 | N35: Venta | O35: 10 / 13 / 2019 /Los Andes
A36: V | B36: Los Andes | C36: Río Aconcagua | D36: Canal | E36: Quilpué | F36: 1.424 | G36: acción | H36: 2.563 | I36: 10213 | J36: =I36/H36 | K36: =J36*1000/$K$2 | L36: =IF(N36="Oferta",J36*$D$60,J36) | M36: 43480 | N36: Venta | O36: 10 / 13 / 2019 /Los Andes
A37: V | B37: Chimbarongo | C37: Río Rapel | D37: Canal | E37: Común | F37: 12.04 | G37: L/s | H37: 12.04 | I37: 122513 | J37: =I37/H37 | K37: =J37*1000/$K$2 | L37: =IF(N37="Oferta",J37*$D$60,J37) | M37: 45792 | N37: Oferta | O37: https://www.aguacircular.cl/00277-060-06
A38: VI | B38: San Vicente TT | C38: Río Rapel | D38: Canal | E38: El Naranjal | F38: 108.5 | G38: L/s | H38: 108.5 | I38: =4000*108.5 | J38: =I38/H38 | K38: =J38*1000/$K$2 | L38: =IF(N38="Oferta",J38*$D$60,J38) | M38: 46157 | N38: Oferta | O38: https://www.gesaguas.cl/derecho/20
A39: VI | B39: Machalí | C39: Río Cachapoal | D39: Canal | E39: San Pedro, Población | F39: 196.56 | G39: L/s | H39: 196.56 | I39: 716924 | J39: =I39/H39 | K39: =J39*1000/$K$2 | L39: =IF(N39="Oferta",J39*$D$60,J39) | M39: 46157 | N39: Oferta | O39: https://www.aguacircular.cl/00540-060-06
A40: VI | B40: Machalí | C40: Río Cachapoal | D40: Canal | E40: San Pedro, Población | F40: 8.1 | G40: L/s | H40: 8.1 | I40: 35400 | J40: =I40/H40 | K40: =J40*1000/$K$2 | L40: =IF(N40="Oferta",J40*$D$60,J40) | M40: 46157 | N40: Oferta | O40: https://www.aguacircular.cl/01265-060-06
A41: VI | B41: Machalí | C41: Río Cachapoal | D41: Canal | E41: San Pedro, Población | F41: 3.85 | G41: L/s | H41: 3.85 | I41: 31230 | J41: =I41/H41 | K41: =J41*1000/$K$2 | L41: =IF(N41="Oferta",J41*$D$60,J41) | M41: 45792 | N41: Oferta | O41: https://www.aguacircular.cl/01119-060-06
A42: VI | B42: Machalí | C42: Río Cachapoal | D42: Canal | E42: San Pedro, Población | F42: 7.33 | G42: L/s | H42: 7.33 | I42: 25000 | J42: =I42/H42 | K42: =J42*1000/$K$2 | L42: =IF(N42="Oferta",J42*$D$60,J42) | M42: 46157 | N42: Oferta | O42: https://www.aguacircular.cl/01281-060-06
A43: VI | B43: Rancagua | C43: Río Cachapoal | D43: Canal | E43: San Pedro, Población | F43: 119 | G43: L/s | H43: 119 | I43: 453540 | J43: =I43/H43 | K43: =J43*1000/$K$2 | L43: =IF(N43="Oferta",J43*$D$60,J43) | M43: 46157 | N43: Oferta | O43: https://www.aguacircular.cl/00532-060-06
A44: VI | B44: Rancagua | C44: Río Cachapoal | D44: Canal | E44: Petterson | F44: 31.2 | G44: L/s | H44: 31.2 | I44: 93600 | J44: =I44/H44 | K44: =J44*1000/$K$2 | L44: =IF(N44="Oferta",J44*$D$60,J44) | M44: 46157 | N44: Oferta | O44: https://www.aguacircular.cl/01361-060-06
A45: VI | B45: San Fernando | C45: Río Tinguiririca | D45: Canal | E45: La Polcura | F45: 24.1 | G45: L/s | H45: 24.1 | I45: 115248 | J45: =I45/H45 | K45: =J45*1000/$K$2 | L45: =IF(N45="Oferta",J45*$D$60,J45) | M45: 46157 | N45: Oferta | O45: https://www.aguacircular.cl/00399-060-06
A46: VI | B46: San Fernando | C46: Río Tinguiririca | D46: Río | E46: Claro | F46: 7 | G46: L/s | H46: 7 | I46: 50000 | J46: =I46/H46 | K46: =J46*1000/$K$2 | L46: =IF(N46="Oferta",J46*$D$60,J46) | M46: 45792 | N46: Oferta | O46: https://www.aguacircular.cl/00546-060-06
A47: VI | B47: Chimbarongo | C47: Estero Chimbarongo | D47: Canal | E47: La Cuesta | F47: 1.75 | G47: L/s | H47: 1.75 | I47: 8227 | J47: =I47/H47 | K47: =J47*1000/$K$2 | L47: =IF(N47="Oferta",J47*$D$60,J47) | M47: 46157 | N47: Oferta | O47: https://www.aguacircular.cl/00447-060-06
A48: VI | B48: Santa Cruz | C48: Estero Chimbarongo | D48: Canal | E48: Santa Cruz y Población | F48: 2.95 | G48: L/s | H48: 2.95 | I48: 43200 | J48: =I48/H48 | K48: =J48*1000/$K$2 | L48: =IF(N48="Oferta",J48*$D$60,J48) | M48: 45792 | N48: Oferta | O48: https://www.aguacircular.cl/00888-060-06
A49: VI | B49: Nancagua | C49: Estero Chimbarongo | D49: Estero | E49: Chimbarongo | F49: 90 | G49: L/s | H49: 90 | I49: 540720 | J49: =I49/H49 | K49: =J49*1000/$K$2 | L49: =IF(N49="Oferta",J49*$D$60,J49) | M49: 46157 | N49: Oferta | O49: https://www.aguacircular.cl/00317-060-06
A50: VI | B50: Chimbarongo | C50: Estero Chimbarongo | D50: Canal | E50: Santa Rita | F50: 12.4 | G50: L/s | H50: 12.4 | I50: 43400 | J50: =I50/H50 | K50: =J50*1000/$K$2 | L50: =IF(N50="Oferta",J50*$D$60,J50) | M50: 46157 | N50: Oferta | O50: https://www.aguacircular.cl/00666-060-06
... A53: VI | B53: Coltauco | C53: Río Rapel | D53: Canal | E53: San Luis de Idahue | F53: 7 | G53: L/s | H53: 7 | I53: 39148 | J53: =I53/H53 | K53: =J53*1000/$K$2 | L53: =IF(N53="Oferta",J53*$D$60,J53) | M53: 46157 | N53: Oferta | O53: https://www.aguacircular.cl/00974-060-06
A54: VI | B54: Coltauco | C54: Río Rapel | D54: Canal | E54: San Luis de Idahue | F54: 113.43 | G54: L/s | H54: =F54 | I54: 851404 | J54: =I54/H54 | K54: =J54*1000/$K$2 | L54: =IF(N54="Oferta",J54*$D$60,J54) | M54: 45792 | N54: Oferta | O54: https://www.aguacircular.cl/00621-060-06
A55: V | B55: Los Andes | C55: Río Aconcagua | D55: Pozo | E55: sin nombre | F55: 50 | G55: L/s | H55: =+F55 | I55: 341250 | J55: =I55/H55 | K55: =J55*1000/$K$2 | L55: =IF(N55="Oferta",J55*$D$60,J55) | M55: 43467 | N55: Venta | O55: 1 / 1 / 2019 / Los Andes
A59: A N Á L I S I S E S T A D Í S T I C O R E F E R E N C I A S
A60: Total Muestra | B60: =SUBTOTAL(102,L5:L57) | C60: Ajuste Oferta a Venta | D60: 0.85
A61: Coef. Asimetría | C61: Curtosis Ajustada
A63: Media Aritmética | C63: =IFERROR(SUBTOTAL(101,L5:L57),"") | D63: M$/(L/s)
A64: Desviación Estándar | C64: =SUBTOTAL(107,L5:L57) | D64: M$/(L/s)
A65: Valor Mínimo | C65: =SUBTOTAL(105,L5:L57) | D65: M$/(L/s)
A66: Valor Máximo | C66: =SUBTOTAL(104,L5:L57) | D66: M$/(L/s)
A68: Intervalo Confianza 95% | C68: =_xlfn.CONFIDENCE.T(0.05,C64,B60) | D68: M$/(L/s)
A69: Límite inferior | C69: =C63-C68 | D69: M$/(L/s)
A70: Límite Superior | C70: =C63+C68 | D70: M$/(L/s)
A72: Mediana | C72: =_xlfn.AGGREGATE(12,7,L6:L55) | D72: M$/(L/s)
A73: Percentil 25 | C73: =_xlfn.AGGREGATE(16,7,L6:L55,0.25) | D73: M$/(L/s)
A74: Percentil 75 | C74: =_xlfn.AGGREGATE(16,7,L6:L55,0.75) | D74: M$/(L/s)

Sheet suelos
A1: fecha | B1: UF | C1: CLIENTE | D1: Región | E1: Comuna | F1: Rol | G1: Uso de Suelo | H1: Clase | I1: m2 | J1: Valor X UF/ m2 | K1: Valor Total | L1: Valor UF X Has | M1: Valor UF Total | N1: OBSERVACIONES | O1: Tasador
A2: =PORTADA!H7 | B2: =UF | C2: =PORTADA!C14 | D2: =PORTADA!H12 | E2: =PORTADA!H11 | F2: =LEGAL!G6 | H2: ='SUELOS '!C46 | I2: ='SUELOS '!E46 | J2: ='SUELOS '!F46 | K2: ='SUELOS '!G46 | L2: =J2*10000 | M2: =L2*I2/10000 | O2: ='RESUMEN VALOR'!B26

Sheet derechos de agua 
A1: fecha | B1: UF | C1: CLIENTE | D1: Región | E1: Comuna | F1: ROL | G1: Acciones /Regadores | H1: Lts/seg | I1: Canal | J1: Valor X Lts/seg | K1: Valor Total | L1: Valor UF X L/s | M1: Valor UF Total | N1: TASADOR
A2: =PORTADA!H7 | B2: =UF | C2: =PORTADA!C14 | D2: =PORTADA!H12 | E2: =PORTADA!H11 | F2: ='AGUA '!C25 | G2: ='AGUA '!F25 | H2: ='AGUA '!G25 | I2: ='AGUA '!B25 | J2: ='AGUA '!I25 | K2: =J2*H2 | L2: =J2/B2 | M2: =L2*H2 | N2: ='RESUMEN VALOR'!B26

Sheet plantas
A1: FECHA TASACION: | B1: UF tasación | C1: CLIENTE | D1: Región | E1: Comuna | F1: Tipo de Cultivo | G1: Variedad | H1: Año Plantación | I1: Densidad plantación (plantas/ha) | J1: Ubicación / Rol | K1: ha | L1: $ Inversion xhas | M1: Años inversion | N1: Vida util (años) | O1: Vida Util Residual | P1: Castigo Comercial % | Q1: $xhas | R1: Total | S1: Total UF | T1: Estado / Observaciones
A2: =PORTADA!H7 | B2: =suelos!B2 | C2: =PORTADA!C14 | D2: =PORTADA!H12 | E2: =PORTADA!H11 | F2: =PLANT!C37 | G2: =PLANT!D37 | H2: =PLANT!F37 | I2: =PLANT!I37 | J2: =PLANT!B37 | K2: =PLANT!J37 | L2: =ROUND(PLANT!W37*USD,-5) | M2: =IF(L2>K2,K2,L2) | N2: 40 | O2: =IF(H2=0,"",N2-(YEAR(PORTADA!$H$7)-H2)) | Q2: =PLANT!AA37 | R2: =Q2*K2 | S2: =R2/B2 | T2: =PLANTACION!K5
A3: =PORTADA!H7 | B3: =PORTADA!$H$8 | C3: =PORTADA!C14 | D3: =PORTADA!H12 | E3: =PORTADA!H11 | F3: =PLANT!C38 | G3: =PLANT!D38 | H3: =PLANT!F38 | I3: =PLANT!I38 | J3: =PLANT!B38 | K3: =PLANT!J38 | L3: =ROUND(PLANT!W38*USD,-5) | N3: 40 | O3: =IF(H3=0,"",N3-(YEAR(PORTADA!$H$7)-H3)) | Q3: =PLANT!AA38 | R3: =Q3*K3 | S3: =R3/B3 | T3: =PLANTACION!K6
A4: =PORTADA!H7 | B4: =PORTADA!$H$8 | C4: =PORTADA!C14 | D4: =PORTADA!H12 | E4: =PORTADA!H11 | F4: =PLANT!C39 | G4: =PLANT!D39 | H4: =PLANT!F39 | I4: =PLANT!I39 | J4: =PLANT!B39 | K4: =PLANT!J39 | L4: =ROUND(PLANT!W39*USD,-5) | M4: =IF(L4>K4,K4,L4) | N4: 40 | O4: =IF(H4=0,"",N4-(YEAR(PORTADA!$H$7)-H4)) | Q4: =PLANT!AA39 | R4: =Q4*K4 | S4: =R4/B4 | T4: =PLANTACION!K7
A5: =PORTADA!H7 | B5: =PORTADA!$H$8 | C5: =PORTADA!C14 | D5: =PORTADA!H12 | E5: =PORTADA!H11 | F5: =PLANT!C40 | G5: =PLANT!D40 | H5: =PLANT!F40 | I5: =PLANT!I40 | J5: =PLANT!B40 | K5: =PLANT!J40 | L5: =ROUND(PLANT!W40*USD,-5) | N5: 40 | O5: =IF(H5=0,"",N5-(YEAR(PORTADA!$H$7)-H5)) | Q5: =PLANT!AA40 | R5: =Q5*K5 | S5: =R5/B5 | T5: =PLANTACION!K8
A6: =PORTADA!H7 | B6: =PORTADA!$H$8 | C6: =PORTADA!C14 | D6: =PORTADA!H12 | E6: =PORTADA!H11 | F6: =PLANT!C41 | G6: =PLANT!D41 | H6: =PLANT!F41 | I6: =PLANT!I41 | J6: =PLANT!B41 | K6: =PLANT!J41 | L6: =ROUND(PLANT!W41*USD,-5) | N6: 40 | O6: =IF(H6=0,"",N6-(YEAR(PORTADA!$H$7)-H6)) | Q6: =PLANT!AA41 | R6: =Q6*K6 | S6: =R6/B6 | T6: =PLANTACION!K9
A7: =PORTADA!H7 | B7: =PORTADA!$H$8 | C7: =PORTADA!C14 | D7: =PORTADA!H12 | E7: =PORTADA!H11 | F7: =PLANT!C42 | G7: =PLANT!D42 | H7: =PLANT!F42 | I7: =PLANT!I42 | J7: =PLANT!B42 | K7: =PLANT!J42 | L7: =ROUND(PLANT!W42*USD,-5) | N7: 40 | O7: =IF(H7=0,"",N7-(YEAR(PORTADA!$H$7)-H7)) | Q7: =PLANT!AA42 | R7: =Q7*K7 | S7: =R7/B7 | T7: =PLANTACION!K10
K8: =SUM(K2:K7) | R8: =SUM(R2:R7)

Sheet PLANT
C1: USD | D1: =PORTADA!H9
C3: Especie | D3: Opex Año | E3: Costo Planta | F3: Años Opex | G3: Plantación | H3: Prep Suelo
C4: Cerezo | D4: 2500 | E4: =ROUNDUP(4000/$D$1,1) | F4: 3 | G4: 0.25 | H4: 1000
C5: Ciruelo | D5: 2000 | E5: =ROUNDUP(4000/$D$1,1) | F5: 3 | G5: 0.25 | H5: 1000
C6: Avellano | D6: 1350 | E6: =ROUNDUP(2700/$D$1,1) | F6: 4 | G6: 0.2 | H6: 1500
C7: Manzano | D7: 2000 | E7: =ROUNDUP(4000/$D$1,1) | F7: 3 | G7: 0.25 | H7: 1000
C8: Peral | D8: 2000 | E8: 5 | F8: 3 | G8: 0.25 | H8: 1000
C9: Nogal | D9: 2200 | E9: =ROUNDUP(6000/$D$1,1) | F9: 3 | G9: 0.25 | H9: 1000
C10: Vid Vinifera | D10: 1000 | E10: =ROUNDDOWN(900/$D$1,1) | F10: 2 | G10: 0.1 | H10: 700
C11: Kiwi | D11: 2000 | E11: =ROUNDUP(4000/$D$1,1) | F11: 2 | G11: 0.25 | H11: 1000
C12: Palto convencional | D12: 2800 | E12: 5 | F12: 4 | G12: 0.25 | H12: 2500
C13: Palto Clonal | D13: 2800 | E13: 14 | F13: 4 | G13: 0.25 | H13: 2500
C14: Uva de mesa | D14: 2500 | E14: 1.3 | F14: 2 | G14: 0.15 | H14: 1000
C15: Uva de mesa® | D15: 2500 | E15: 2.5 | F15: 2 | G15: 0.15 | H15: 1000
C27: Estructura | D27: USD/estruc
C28: Parron estándar | D28: 7000
C29: Open Gable | D29: 10000
C30: Espaldera | D30: 3500
C31: Alambrado Tutor | D31: 1500
C32: No | D32: 0
A36: Predio | B36: ROL | C36: Especie | D36: Variedad | E36: Conducción | F36: Año Plantación | G36: eh (m) | H36: sh (m) | I36: Plantas x ha | J36: Superf. Plantada ha | K36: SUPERF CON RIEGO | L36: Estructura | M36: Riego | N36: Valor Planta | O36: Costo Plantación | P36: Preparación suelo | Q36: Costo Estructura | R36: Edad (años) | S36: Años Opex | T36: Opex a considerar | U36: Capex/año | V36: Capex Total | W36: Costo Reposición /ha | X36: % CASTIGO | Y36: Valor Ajustado/ha | Z36: VALOR TOTAL USD | AA36: VALOR Ch$/ha | AB36: VALOR TOTAL $
