Workbook

Sheet Cliente
A4: INFORME AGROECONÓMICO
A8: ANTECEDENTES GENERALES
A10: Cliente | E10: RUT
A11: Ejecutivo | E11: Fecha Visita
A12: Sucursal | E12: Fecha Emisión Informe
A13: Agrónomo Informante | E13: N° Solicitud
A16: ESTRUCTURA PRODUCTIVA (TEMPORADA)
A18: Especie | B18: Escala Productiva Actual | D18: Consolidación productiva | F18: Condición de Tenencia de los Suelos (ha)
B19: Superficie (ha) | D19: % | F19: Propio | H19: Arriendo | I19: Otros
A24: Total (ha)
A26: RESUMEN RESULTADOS DE TEMPORADA
A28: ITEM | B28: Última temporada | E28: 25/26 | F28: Proyección Corto Plazo | I28: 26/27
B29: M$ | D29: UF | F29: M$ | H29: UF
A30: Ingresos Operacionales
A31: Costos Directos
A32: Margen Bruto
A33: Costos Indirectos
A34: RESULTADO OPERACIONAL NETO
A36: Temporada | B36: 2025/26 Real | C36: 2026/27 | D36: 2027/28 | E36: 2028/29 | F36: 2029/30 | G36: 2030/31 | H36: 2031/32 | I36: 2032/33
A37: RESULTADO OPERACIONAL NETO M$ | B37: ='Flujo proyectado '!F110 -> 0 | C37: ='Flujo proyectado '!G110 -> 0 | D37: ='Flujo proyectado '!H110 -> 0 | E37: ='Flujo proyectado '!I110 -> 0 | F37: ='Flujo proyectado '!J110 -> 0 | G37: ='Flujo proyectado '!K110 -> 0 | H37: ='Flujo proyectado '!L110 -> 0 | I37: ='Flujo proyectado '!M110 -> 0
A39: IMAGEN EMPLAZAMIENTO UNIDAD PRINCIPAL

Sheet Dotación de recursos
A2: DOTACIÓN DE RECURSOS
A4: SUELOS
A6: Cliente
A7: Predio
A8: Dominio
A9: Rol Avalúo
A10: Comuna
A11: Inscripción de Dominio
A12: Clase Uso | B12: RIEGO | C12: SECANO | D12: TOTAL | E12: RIEGO | F12: SECANO | G12: TOTAL | H12: RIEGO | I12: SECANO | J12: TOTAL | K12: RIEGO | L12: SECANO | M12: TOTAL
A13: I-II | D13: =B13+C13 -> 0 | G13: =E13+F13 -> 0 | J13: =H13+I13 -> 0 | M13: =K13+L13 -> 0
A14: III-IV | D14: =B14+C14 -> 0 | G14: =E14+F14 -> 0 | J14: =H14+I14 -> 0 | M14: =K14+L14 -> 0
A15: V-VI | D15: =B15+C15 -> 0 | G15: =E15+F15 -> 0 | J15: =H15+I15 -> 0 | M15: =K15+L15 -> 0
A16: VII-VIII | D16: =B16+C16 -> 0 | G16: =E16+F16 -> 0 | J16: =H16+I16 -> 0 | M16: =K16+L16 -> 0
A17: Total ha físicas | B17: =SUM(B13:B16) -> 0 | C17: =SUM(C13:C16) -> 0 | D17: =SUM(D13:D16) -> 0 | E17: =SUM(E13:E16) -> 0 | F17: =SUM(F13:F16) -> 0 | G17: =SUM(G13:G16) -> 0 | H17: =SUM(H13:H16) -> 0 | I17: =SUM(I13:I16) -> 0 | ... M17: =SUM(M13:M16) -> 0
A19: AGUAS DE RIEGO
A21: Predio | B21: Comuna | C21: Tipo de Fuente | D21: Nombre de la fuente | E21: Dominio | F21: Cantidad (D°/acciones) | G21: Caudal nominal L/s | H21: Caudal Real L/s | I21: Datos Inscripción CBR | M21: Propietario
I22: Fojas | J22: Número | K22: Año | L22: CBR
A27: TOTAL AGUAS DISPONIBLES | H27: =SUM(H23:H26) -> 0
A29: ESTIMACIÓN REQUERIMIENTO AGUAS DE RIEGO
A31: Predio | C31: Comuna
A32: Especie/variedad | B32: Año Plantación | C32: Superficie (ha) | D32: Sistema de Riego | E32: Eficiencia Sis. Riego | F32: ETo Máximo-mm (enero) | G32: Coef. Cultivo Kc (enero) | H32: Requerimiento Q Maximo L/s/ha | I32: Requerimiento Total por Plantación L/s | J32: Requerimiento Total Predio L/s | K32: Disponibilidad Total Predio L/s | L32: Densidad de plantación
J33: =SUM(I33:I36) -> 0
A37: Superficie Total Plantada (ha) | C37: =SUM(C33:C36) -> 0
A39: DOTACIÓN DE MAQUINARIA E INFRESTRUCTURA
A41: Tipo de Maquinaria | B41: Cantidad | C41: Estado | F41: Infraestructura | G41: Cantidad | H41: Estado | K41: Infraestructura | L41: Cantidad | M41: Estado
A46: COMENTARIOS DOTACIÓN DE RECURSOS

Sheet Inversión
A2: INVERSIONES
A4: Proyecto | B4: Año | C4: Superficie (ha) | D4: Item | E4: Cantidad/ha | F4: Costo unitario USD | G4: Costo unitario USD/ha | H4: Costo Inversión Total USD | I4: Costo Inversión $ | J4: % En relación al Total
J5: =I5/$I$15 -> #DIV/0!
J6: =I6/$I$15 -> #DIV/0!
J7: =I7/$I$15 -> #DIV/0!
J8: =I8/$I$15 -> #DIV/0!
J9: =I9/$I$15 -> #DIV/0!
J10: =I10/$I$15 -> #DIV/0!
J11: =I11/$I$15 -> #DIV/0!
J12: =I12/$I$15 -> #DIV/0!
J13: =I13/$I$15 -> #DIV/0!
J14: =I14/$I$15 -> #DIV/0!
A15: Total | C15: =SUM(C5:C14) -> 0 | G15: =SUM(G5:G14) -> 0 | H15: =SUM(H5:H14) -> 0 | I15: =SUM(I5:I14) -> 0 | J15: =SUM(J5:J14) -> #DIV/0!
A17: COMENTARIOS INVERSIONES

Sheet Estructura Productiva
A2: ESTRUCTURA PRODUCTIVA
A4: PLANTACIONES AL 2026
A6: Especie | B6: Variedad | C6: Año Plantación | D6: Superficie (ha) | E6: Sistema Conducción | F6: Predio | G6: Dominio | H6: Riego | I6: Estado | J6: Densidad plantación
A11: Superficie Total Plantada (ha) | D11: =SUM(D7:D10) -> 0
A13: RESUMEN SUPERFICIE PLANTADA
A15: Resumen superficie | B15: Propietario (ha) | C15: Arrendatario (ha) | D15: Total (ha) | E15: % por especie | F15: Plena Producción (ha) | G15: Rendimientos Crecientes (ha) | H15: Formación (ha) | I15: Proyectos de Plantación (ha) | J15: Superficie Total con Proyectos (ha)
D16: =SUM(B16:C16) -> 0
D17: =SUM(B17:C17) -> 0
D18: =SUM(B18:C18) -> 0
D19: =SUM(B19:C19) -> 0
A20: Total | B20: =SUM(B16:B19) -> 0 | C20: =SUM(C16:C19) -> 0 | D20: =SUM(D16:D19) -> 0 | F20: =SUM(F16:F19) -> 0 | G20: =SUM(G16:G19) -> 0 | H20: =SUM(H16:H19) -> 0 | I20: =SUM(I16:I19) -> 0 | J20: =SUM(J16:J19) -> 0
A21: Porcentajes (%) | B21: 1
A23: Comentarios Plantaciones:
A28: SISTEMA DE PRODUCCIÓN EMPLEADO
A30: Especie | B30: Sistema de producción | C30: Densidad de plantación | D30: Sistema de riego | E30: Variedades con Royalty | F30: Considera Techos o similares | G30: Sistema de Contra heladas | H30: Nivel Tecnológico | I30: Nivel Homogeneidad | J30: Nivel Productivo Promedio
A36: SISTEMA DE COMERCIALIZACIÓN
A38: Especie | B38: Empresas comercializadoras | C38: Comercialización | D38: Mercado | E38: Periodo de Cosecha desde-hasta | G38: Periodo Liquidaciones desde-hasta | I38: Proceso | J38: Gestión de Exportación

Sheet Flujo proyectado 
A2: PROYECCIÓN LARGO PLAZO
A3: Cliente:
A4: Tipo de cambio: | C4: $/USD | D4: 2023/24 | E4: 2025/26
D5: $ | E5: $
D7: Historicos | F7: Proyección
A8: Assumptions | D8: 2023/24 | E8: 2024/25 | F8: 2025/26 | G8: 2026/27 | H8: 2027/28 | I8: 2028/29 | J8: 2029/30 | K8: 2030/31 | L8: 2031/32 | M8: 2032/33 | N8: 2033/34
D9: Real | E9: Real | F9: Preliminar | G9: Projection
A10: Especie/Variedad/Año
A11: Superficie (ha)
A12: Precio exportación (USD/Kg)
A13: Precio Mercado Interno (USD/Kg)
A14: Producción/Rendimiento (Kg/ha)
A15: Ratio Exportación (%)
A16: Costos (USD/ha)
A17: Producción Total (kg)
A18: Ingresos Exportación
A19: Ingresos Mercado Interno
A20: Especie/Variedad/Año
A21: Superficie (ha)
... A49: Ingresos Mercado Interno
D54: 2023/24 | E54: 2024/25 | F54: 2025/26 | G54: 2026/27 | H54: 2027/28 | I54: 2028/29 | J54: 2029/30 | K54: 2030/31 | L54: 2031/32 | M54: 2032/33 | N54: 2033/34
A55: RESUMEN DE INDICADORES GENERALES | D55: Real | E55: Real | F55: Projection
A56: Superficie (ha) | D56: =SUM(D57:D60) -> 0 | E56: =SUM(E57:E60) -> 0 | F56: =SUM(F57:F60) -> 0 | G56: =SUM(G57:G60) -> 0 | H56: =SUM(H57:H60) -> 0 | I56: =SUM(I57:I60) -> 0 | J56: =SUM(J57:J60) -> 0 | K56: =SUM(K57:K60) -> 0 | ... N56: =SUM(N57:N60) -> 0
D57: =D11 -> 0 | E57: =E11 -> 0 | F57: =F11 -> 0 | G57: =G11 -> 0 | H57: =H11 -> 0 | I57: =I11 -> 0 | J57: =J11 -> 0 | K57: =K11 -> 0 | ... N57: =N11 -> 0
D58: =D21 -> 0 | E58: =E21 -> 0 | F58: =F21 -> 0 | G58: =G21 -> 0 | H58: =H21 -> 0 | I58: =I21 -> 0 | J58: =J21 -> 0 | K58: =K21 -> 0 | ... N58: =N21 -> 0
D59: =D31 -> 0 | E59: =E31 -> 0 | F59: =F31 -> 0 | G59: =G31 -> 0 | H59: =H31 -> 0 | I59: =I31 -> 0 | J59: =J31 -> 0 | K59: =K31 -> 0 | ... N59: =N31 -> 0
D60: =D41 -> 0 | E60: =E41 -> 0 | F60: =F41 -> 0 | G60: =G41 -> 0 | H60: =H41 -> 0 | I60: =I41 -> 0 | J60: =J41 -> 0 | K60: =K41 -> 0 | ... N60: =N41 -> 0
A61: Producción Total | D61: =SUM(D62:D65) -> 0 | E61: =SUM(E62:E65) -> 0 | F61: =SUM(F62:F65) -> 0 | G61: =SUM(G62:G65) -> 0 | H61: =SUM(H62:H65) -> 0 | I61: =SUM(I62:I65) -> 0 | J61: =SUM(J62:J65) -> 0 | K61: =SUM(K62:K65) -> 0 | ... N61: =SUM(N62:N65) -> 0
D62: =D17 -> 0 | E62: =E17 -> 0 | F62: =F17 -> 0 | G62: =G17 -> 0 | H62: =H17 -> 0 | I62: =I17 -> 0 | J62: =J17 -> 0 | K62: =K17 -> 0 | ... N62: =N17 -> 0
D63: =D27 -> 0 | E63: =E27 -> 0 | F63: =F27 -> 0 | G63: =G27 -> 0 | H63: =H27 -> 0 | I63: =I27 -> 0 | J63: =J27 -> 0 | K63: =K27 -> 0 | ... N63: =N27 -> 0
D64: =D37 -> 0 | E64: =E37 -> 0 | F64: =F37 -> 0 | G64: =G37 -> 0 | H64: =H37 -> 0 | I64: =I37 -> 0 | J64: =J37 -> 0 | K64: =K37 -> 0 | ... N64: =N37 -> 0
D65: =D47 -> 0 | E65: =E47 -> 0 | F65: =F47 -> 0 | G65: =G47 -> 0 | H65: =H47 -> 0 | I65: =I47 -> 0 | J65: =J47 -> 0 | K65: =K47 -> 0 | ... N65: =N47 -> 0
A66: Producción promedio (Kg/ha)
D67: =IFERROR(D62/D57,0) -> 0 | E67: =IFERROR(E62/E57,0) -> 0 | F67: =IFERROR(F62/F57,0) -> 0 | G67: =IFERROR(G62/G57,0) -> 0 | H67: =IFERROR(H62/H57,0) -> 0 | I67: =IFERROR(I62/I57,0) -> 0 | J67: =IFERROR(J62/J57,0) -> 0 | K67: =IFERROR(K62/K57,0) -> 0 | ... N67: =IFERROR(N62/N57,0) -> 0
D68: =IFERROR(D63/D58,0) -> 0 | E68: =IFERROR(E63/E58,0) -> 0 | F68: =IFERROR(F63/F58,0) -> 0 | G68: =IFERROR(G63/G58,0) -> 0 | H68: =IFERROR(H63/H58,0) -> 0 | I68: =IFERROR(I63/I58,0) -> 0 | J68: =IFERROR(J63/J58,0) -> 0 | K68: =IFERROR(K63/K58,0) -> 0 | ... N68: =IFERROR(N63/N58,0) -> 0
D69: =IFERROR(D64/D59,0) -> 0 | E69: =IFERROR(E64/E59,0) -> 0 | F69: =IFERROR(F64/F59,0) -> 0 | G69: =IFERROR(G64/G59,0) -> 0 | H69: =IFERROR(H64/H59,0) -> 0 | I69: =IFERROR(I64/I59,0) -> 0 | J69: =IFERROR(J64/J59,0) -> 0 | K69: =IFERROR(K64/K59,0) -> 0 | ... N69: =IFERROR(N64/N59,0) -> 0
D70: =IFERROR(D65/D60,0) -> 0 | E70: =IFERROR(E65/E60,0) -> 0 | F70: =IFERROR(F65/F60,0) -> 0 | G70: =IFERROR(G65/G60,0) -> 0 | H70: =IFERROR(H65/H60,0) -> 0 | I70: =IFERROR(I65/I60,0) -> 0 | J70: =IFERROR(J65/J60,0) -> 0 | K70: =IFERROR(K65/K60,0) -> 0 | ... N70: =IFERROR(N65/N60,0) -> 0
A71: Precio de venta promedio (USD/Kg)
D72: =((D12+D13)/2) -> 0 | E72: =((E12+E13)/2) -> 0 | F72: =((F12+F13)/2) -> 0 | G72: =((G12+G13)/2) -> 0 | H72: =((H12+H13)/2) -> 0 | I72: =((I12+I13)/2) -> 0 | J72: =((J12+J13)/2) -> 0 | K72: =((K12+K13)/2) -> 0 | ... N72: =((N12+N13)/2) -> 0
D73: =((D22+D23)/2) -> 0 | E73: =((E22+E23)/2) -> 0 | F73: =((F22+F23)/2) -> 0 | G73: =((G22+G23)/2) -> 0 | H73: =((H22+H23)/2) -> 0 | I73: =((I22+I23)/2) -> 0 | J73: =((J22+J23)/2) -> 0 | K73: =((K22+K23)/2) -> 0 | ... N73: =((N22+N23)/2) -> 0
D74: =((D32+D33)/2) -> 0 | E74: =((E32+E33)/2) -> 0 | F74: =((F32+F33)/2) -> 0 | G74: =((G32+G33)/2) -> 0 | H74: =((H32+H33)/2) -> 0 | I74: =((I32+I33)/2) -> 0 | J74: =((J32+J33)/2) -> 0 | K74: =((K32+K33)/2) -> 0 | ... N74: =((N32+N33)/2) -> 0
D75: =((D42+D43)/2) -> 0 | E75: =((E42+E43)/2) -> 0 | F75: =((F42+F43)/2) -> 0 | G75: =((G42+G43)/2) -> 0 | H75: =((H42+H43)/2) -> 0 | I75: =((I42+I43)/2) -> 0 | J75: =((J42+J43)/2) -> 0 | K75: =((K42+K43)/2) -> 0 | ... N75: =((N42+N43)/2) -> 0
A76: Costo Promedio (USD/ha)
D77: =D16 -> 0 | E77: =E16 -> 0 | F77: =F16 -> 0 | G77: =G16 -> 0 | H77: =H16 -> 0 | I77: =I16 -> 0 | J77: =J16 -> 0 | K77: =K16 -> 0 | ... N77: =N16 -> 0
D78: =D26 -> 0 | E78: =E26 -> 0 | F78: =F26 -> 0 | G78: =G26 -> 0 | H78: =H26 -> 0 | I78: =I26 -> 0 | J78: =J26 -> 0 | K78: =K26 -> 0 | ... N78: =N26 -> 0
D79: =D36 -> 0 | E79: =E36 -> 0 | F79: =F36 -> 0 | G79: =G36 -> 0 | H79: =H36 -> 0 | I79: =I36 -> 0 | J79: =J36 -> 0 | K79: =K36 -> 0 | ... N79: =N36 -> 0
D80: =D46 -> 0 | E80: =E46 -> 0 | F80: =F46 -> 0 | G80: =G46 -> 0 | H80: =H46 -> 0 | I80: =I46 -> 0 | J80: =J46 -> 0 | K80: =K46 -> 0 | ... N80: =N46 -> 0
A81: Costo unitario (USD/Kg)
D82: =IFERROR(D16/D14,0) -> 0 | E82: =IFERROR(E16/E14,0) -> 0 | F82: =IFERROR(F16/F14,0) -> 0 | G82: =IFERROR(G16/G14,0) -> 0 | H82: =IFERROR(H16/H14,0) -> 0 | I82: =IFERROR(I16/I14,0) -> 0 | J82: =IFERROR(J16/J14,0) -> 0 | K82: =IFERROR(K16/K14,0) -> 0 | ... N82: =IFERROR(N16/N14,0) -> 0
D83: =IFERROR(D26/D24,0) -> 0 | E83: =IFERROR(E26/E24,0) -> 0 | F83: =IFERROR(F26/F24,0) -> 0 | G83: =IFERROR(G26/G24,0) -> 0 | H83: =IFERROR(H26/H24,0) -> 0 | I83: =IFERROR(I26/I24,0) -> 0 | J83: =IFERROR(J26/J24,0) -> 0 | K83: =IFERROR(K26/K24,0) -> 0 | ... N83: =IFERROR(N26/N24,0) -> 0
D84: =IFERROR(D36/D34,0) -> 0 | E84: =IFERROR(E36/E34,0) -> 0 | F84: =IFERROR(F36/F34,0) -> 0 | G84: =IFERROR(G36/G34,0) -> 0 | H84: =IFERROR(H36/H34,0) -> 0 | I84: =IFERROR(I36/I34,0) -> 0 | J84: =IFERROR(J36/J34,0) -> 0 | K84: =IFERROR(K36/K34,0) -> 0 | ... N84: =IFERROR(N36/N34,0) -> 0
D85: =IFERROR(D46/D44,0) -> 0 | E85: =IFERROR(E46/E44,0) -> 0 | F85: =IFERROR(F46/F44,0) -> 0 | G85: =IFERROR(G46/G44,0) -> 0 | H85: =IFERROR(H46/H44,0) -> 0 | I85: =IFERROR(I46/I44,0) -> 0 | J85: =IFERROR(J46/J44,0) -> 0 | K85: =IFERROR(K46/K44,0) -> 0 | ... N85: =IFERROR(N46/N44,0) -> 0
A87: ESTADO DE RESULTADOS | D87: 2023/24 | E87: 2024/25 | F87: 2025/26 | G87: 2026/27 | H87: 2027/28 | I87: 2028/29 | J87: 2029/30 | K87: 2030/31 | L87: 2031/32 | M87: 2032/33 | N87: 2033/34
D88: Real | E88: Real | F88: Projection
A89: Ingresos | D89: =SUM(D90:D93) -> 0 | E89: =SUM(E90:E93) -> 0 | F89: =SUM(F90:F93) -> 0 | G89: =SUM(G90:G93) -> 0 | H89: =SUM(H90:H93) -> 0 | I89: =SUM(I90:I93) -> 0 | J89: =SUM(J90:J93) -> 0 | K89: =SUM(K90:K93) -> 0 | ... N89: =SUM(N90:N93) -> 0
D90: =D18+D19 -> 0 | E90: =E18+E19 -> 0 | F90: =F18+F19 -> 0 | G90: =G18+G19 -> 0 | H90: =H18+H19 -> 0 | I90: =I18+I19 -> 0 | J90: =J18+J19 -> 0 | K90: =K18+K19 -> 0 | ... N90: =N18+N19 -> 0
D91: =D28+D29 -> 0 | E91: =E28+E29 -> 0 | F91: =F28+F29 -> 0 | G91: =G28+G29 -> 0 | H91: =H28+H29 -> 0 | I91: =I28+I29 -> 0 | J91: =J28+J29 -> 0 | K91: =K28+K29 -> 0 | ... N91: =N28+N29 -> 0
D92: =D38+D39 -> 0 | E92: =E38+E39 -> 0 | F92: =F38+F39 -> 0 | G92: =G38+G39 -> 0 | H92: =H38+H39 -> 0 | I92: =I38+I39 -> 0 | J92: =J38+J39 -> 0 | K92: =K38+K39 -> 0 | ... N92: =N38+N39 -> 0
D93: =D48+D49 -> 0 | E93: =E48+E49 -> 0 | F93: =F48+F49 -> 0 | G93: =G48+G49 -> 0 | H93: =H48+H49 -> 0 | I93: =I48+I49 -> 0 | J93: =J48+J49 -> 0 | K93: =K48+K49 -> 0 | ... N93: =N48+N49 -> 0
A94: Costos Totales | D94: =SUM(D95:D98) -> 0 | E94: =SUM(E95:E98) -> 0 | F94: =SUM(F95:F98) -> 0 | G94: =SUM(G95:G98) -> 0 | H94: =SUM(H95:H98) -> 0 | I94: =SUM(I95:I98) -> 0 | J94: =SUM(J95:J98) -> 0 | K94: =SUM(K95:K98) -> 0 | ... N94: =SUM(N95:N98) -> 0
D95: =D16*D11 -> 0 | E95: =E16*E11 -> 0 | F95: =F16*F11 -> 0 | G95: =G16*G11 -> 0 | H95: =H16*H11 -> 0 | I95: =I16*I11 -> 0 | J95: =J16*J11 -> 0 | K95: =K16*K11 -> 0 | ... N95: =N16*N11 -> 0
D96: =D26*D21 -> 0 | E96: =E26*E21 -> 0 | F96: =F26*F21 -> 0 | G96: =G26*G21 -> 0 | H96: =H26*H21 -> 0 | I96: =I26*I21 -> 0 | J96: =J26*J21 -> 0 | K96: =K26*K21 -> 0 | ... N96: =N26*N21 -> 0
D97: =D36*D31 -> 0 | E97: =E36*E31 -> 0 | F97: =F36*F31 -> 0 | G97: =G36*G31 -> 0 | H97: =H36*H31 -> 0 | I97: =I36*I31 -> 0 | J97: =J36*J31 -> 0 | K97: =K36*K31 -> 0 | ... N97: =N36*N31 -> 0
D98: =D46*D41 -> 0 | E98: =E46*E41 -> 0 | F98: =F46*F41 -> 0 | G98: =G46*G41 -> 0 | H98: =H46*H41 -> 0 | I98: =I46*I41 -> 0 | J98: =J46*J41 -> 0 | K98: =K46*K41 -> 0 | ... N98: =N46*N41 -> 0
A100: Costo Generales | D100: =SUM(D101:D102) -> 0 | E100: =SUM(E101:E102) -> 0 | F100: =SUM(F101:F102) -> 0 | G100: =SUM(G101:G102) -> 0 | H100: =SUM(H101:H102) -> 0 | I100: =SUM(I101:I102) -> 0 | J100: =SUM(J101:J102) -> 0 | K100: =SUM(K101:K102) -> 0 | ... N100: =SUM(N101:N102) -> 0
A101: Administración
A102: Gastos Generales
A104: ESTADO DE RESULTADOS | D104: 2023/24 | E104: 2024/25 | F104: 2025/26 | G104: 2026/27 | H104: 2027/28 | I104: 2028/29 | J104: 2029/30 | K104: 2030/31 | L104: 2031/32 | M104: 2032/33 | N104: 2033/34
D105: Real | E105: Real | G105: Projection
A106: Ingresos totales | D106: =D89 -> 0 | E106: =E89 -> 0 | F106: =F89 -> 0 | G106: =G89 -> 0 | H106: =H89 -> 0 | I106: =I89 -> 0 | J106: =J89 -> 0 | K106: =K89 -> 0 | ... N106: =N89 -> 0
A107: Costos Totales | D107: =D94 -> 0 | E107: =E94 -> 0 | F107: =F94 -> 0 | G107: =G94 -> 0 | H107: =H94 -> 0 | I107: =I94 -> 0 | J107: =J94 -> 0 | K107: =K94 -> 0 | ... N107: =N94 -> 0
A108: Costo General | D108: =D100 -> 0 | E108: =E100 -> 0 | F108: =F100 -> 0 | G108: =G100 -> 0 | H108: =H100 -> 0 | I108: =I100 -> 0 | J108: =J100 -> 0 | K108: =K100 -> 0 | ... N108: =N100 -> 0
A110: EBITDA | D110: =D106-D107-D108 -> 0 | E110: =E106-E107-E108 -> 0 | F110: =F106-F107-F108 -> 0 | G110: =G106-G107-G108 -> 0 | H110: =H106-H107-H108 -> 0 | I110: =I106-I107-I108 -> 0 | J110: =J106-J107-J108 -> 0 | K110: =K106-K107-K108 -> 0 | ... N110: =N106-N107-N108 -> 0
A111: EBITDA/ha | D111: =IFERROR(D110/D56,0) -> 0 | E111: =IFERROR(E110/E56,0) -> 0 | F111: =IFERROR(F110/F56,0) -> 0 | G111: =IFERROR(G110/G56,0) -> 0 | H111: =IFERROR(H110/H56,0) -> 0 | I111: =IFERROR(I110/I56,0) -> 0 | J111: =IFERROR(J110/J56,0) -> 0 | K111: =IFERROR(K110/K56,0) -> 0 | ... N111: =IFERROR(N110/N56,0) -> 0
A112: EBITDA/Ingresos | D112: =(D110/D106)*100 -> #DIV/0! | E112: =(E110/E106)*100 -> #DIV/0! | F112: =(F110/F106)*100 -> #DIV/0! | G112: =(G110/G106)*100 -> #DIV/0! | H112: =(H110/H106)*100 -> #DIV/0! | I112: =(I110/I106)*100 -> #DIV/0! | J112: =(J110/J106)*100 -> #DIV/0! | K112: =(K110/K106)*100 -> #DIV/0! | ... N112: =(N110/N106)*100 -> #DIV/0!
A114: Nivel de Respaldo de Ventas | D114: 2023/24
A115: Monto de Ingresos Respaldado
A116: % de Respaldo
A118: Comentarios

Sheet Comentarios generales Opinion
A2: COMENTARIOS GENERALES
A4: Gestión Administrativa y Productiva | E4: CALIFICACIÓN
A11: Conocimiento y Manejo de Canales Comerciales | E11: CALIFICACIÓN
A18: Calidad de los Activos Productivos Disponibles | E18: CALIFICACIÓN
A25: Conclusión Final | E25: CALIFICACIÓN

Sheet Anexo 
B2: RESULTADO REAL TEMPORADA
B3: Especie | D3: Producción Exportación (Kg) | E3: Producción Merc. Interno (Kg) | F3: ProduccIón total (Kg) | G3: Ventas Exportación ($) | H3: Ventas Merc. Interno ($) | I3: Total ventas ($) | J3: Total ventas USD | K3: Costos Directos Totales por Rubro ($) | L3: Costos Directos Totales por Rubro USD | M3: Margen Bruto ($)
F4: =D4+E4 -> 0 | I4: 0 | K4: 0 | M4: =I4-K4 -> 0
F5: =D5+E5 -> 0 | I5: =G5+H5 -> 0 | M5: =I5-K5 -> 0
F6: =D6+E6 -> 0 | I6: =G6+H6 -> 0 | M6: =I6-K6 -> 0
F7: =D7+E7 -> 0 | I7: =G7+H7 -> 0 | M7: =I7-K7 -> 0
F8: =SUM(F4:F7) -> 0 | I8: =SUM(I4:I7) -> 0 | K8: =SUM(K4:K7) -> 0 | M8: =SUM(M4:M7) -> 0
K9: Administracion $
K10: Gastos generales $
K11: EBITDA $ | M11: =M8-M10-M9 -> 0
B13: RESULTRADO PRELIMINAR TEMPORADA
B14: Especie | D14: Producción exportación (Kg) | E14: Producción Merc. Interno (Kg) | F14: Producción Total (Kg) | G14: Ventas Exportación ($) | H14: Ventas Merc. Interno ($) | I14: Total ventas ($) | J14: Total ventas USD | K14: Costos Directos Totales por Rubro ($) | L14: Costos Directos Totales por Rubro USD | M14: Margen bruto ($)
F15: =D15+E15 -> 0 | I15: =G15+H15 -> 0 | M15: =I15-K15 -> 0
F16: =D16+E16 -> 0 | I16: =G16+H16 -> 0 | M16: =I16-K16 -> 0
F17: =D17+E17 -> 0 | I17: =G17+H17 -> 0 | M17: =I17-K17 -> 0
F18: =D18+E18 -> 0 | I18: =G18+H18 -> 0 | M18: =I18-K18 -> 0
F19: =SUM(F15:F18) -> 0 | I19: =SUM(I15:I18) -> 0 | K19: =SUM(K15:K18) -> 0 | M19: =SUM(M15:M18) -> 0
K20: Administracion $
K21: Gastos generales $
K22: EBITDA $ | M22: =M19-M21-M20 -> 0
